Workbook

Sheet 表格说明
A1: 中国银保监会银行业金融机构监管数据标准化规范 数据结构一览表说明
A2: 1. 标准化数据结构以表形式组织。一个或多个表归属于一个分类，每个表包含多个数据项。
A3: 2. 数据项已按表进行分类组合，通过使用最左侧导航按钮，可以展开或隐藏各表数据项，便于查看。
A4: 3. 数据结构备注中PK为监管部门作为唯一性约束的参考条件，含有多个PK的，表示联合主键的参考，并不作为主外键唯一性约束的要求，银行机构可根据数据实际入库情况作出调整。
A5: 4. “数据元说明”定义数据项的类型及长度的表示形式。
A6: 5. 数据项中备注“关联数据项：[表名].[数据项名]”表示该数据项取值的参考数据项。例如“关联数据项:机构信息表.内部机构号”表示该数据项应和“机构信息表”中的“内部机构号”数据项取值一致。
A7: 6. Cn 表示n个字符的固定长度，相应的字符长度由字符编码集确定。UTF-8的中文字符占3个字节。
A8: 7. C..n 表示最多为n个字符的可变长度。UTF-8的中文字符占3个字节。
A9: 8. I 表示整数可计算形式。
A10: 9. I..n 表示最多为n位的整数可计算形式。
A11: 10. Dw.d 表示十进制小数可计算形式，w表示包含小数点前后字符位在内的整个字段最多字符位数，d表示小数点后的最多字符位数。
A12: 11. F 表示任意长度浮点数。
A13: 12.本规范中涉及到的“明细科目编号”及“明细科目名称”均为该笔业务数据关联的主要会计科目名称，同一条数据涉及多个会计科目的仅报送该笔业务指向的主要会计科目，并不作为总分核对的分类指标。

Sheet 表结构总览
F1: 表编号 | G1: 报送模式 | H1: 报送要求 | I1: 修改说明
A2: 主题 | B2: 公共信息 | C2: 001
A3: 表名 | D3: JGXXB | E3: 机构信息表 | F3: 101 | G3: 全量表，报送截止采集日有效的数据以及与上一采集日期间失效的数据。 | H3: 本表报送银行机构或业务中心信息，业务中心包含管理机构、营业机构、内设机构、虚拟机构。对于营业机构、内设机构、虚拟机构，银行机构代码、金融许可证号等字段可以取上级机构或者本级实体机构对应的信息。境外机构也需要报送，根据实际情况无法填报的字段可以为空。子公司不必报送。机构永久关停、撤销等情况的，在报送最后状态的次月可不再报送。 | I3: 修改
D4: YGB | E4: 员工表 | F4: 102 | G4: 全量表，报送截止采集日有效的数据以及与上一采集日期间失效的数据。 | H4: 在职类正式/非正式员工需每月报送，非正式员工包括合同制、劳务派遣员工。员工状态转为离职、退休、开除、死亡、调出等的，在报送该员工最后状态的次月可不再报送。子公司员工不用报送，调动至子公司的员工按离职报送。董事、监事不用报送。 | I4: 修改
D5: GYB | E5: 柜员表 | F5: 103 | G5: 全量表，报送截止采集日有效的数据以及与上一采集日期间失效的数据。 | H5: 包含实体柜员和虚拟柜员。为虚拟柜员时，工号、银行机构代码等字段依业务实际填列或留为缺失值，如报送虚拟柜员，则通过“柜员类型”字段进行区分；柜员状态转为注销、无效等时，可在报送该条数据最终状态的次月不再报送。 | I5: 修改
D6: GWXXB | E6: 岗位信息表 | F6: 104 | G6: 全量表，报送截止采集日有效的数据以及与上一采集日期间失效的数据。 | H6: 银行机构内设立的所有岗位的相关信息，至少应包括核心和人力资源系统中的所有岗位信息。撤销的岗位于次月不再报送。 | I6: 修改
D7: JGGXB | E7: 机构关系表 | F7: 105 | G7: 全量表，报送截止采集日有效的数据以及与上一采集日期间失效的数据。 | H7: 机构关系表报送范围应包括所有进行账务处理的机构，至少应包括总行、分行、支行等实体机构和省级汇总、地市级汇总、法人汇总、分行汇总。会计全科目表中的机构在机构关系表中都需要报送，每次全量报送。 | I7: 修改
D8: GDXXB | E8: 股东信息表 | F8: 106 | G8: 全量表，报送截止采集日银行机构最新持股股东及持股比例等信息。 | H8: 本表应填报银行自身的股东。对于已上市银行，需填报持有或控制1%以上股份或表决权，及虽不足1%但对商业银行经营管理有重大影响的股东。未上市银行机构应报送所有的对公、个人股东信息。 | I8: 修改
B9: 客户信息 | C9: 002
D10: GRJCXXB | E10: 个人基础信息表 | F10: 201 | G10: 全量表，报送截止采集日有效的数据以及与上一采集日期间失效的数据。 | H10: 个人基础信息，包括本行客户及本行客户的担保、配偶、亲属关系所涉及到的个人客户信息。不再列为银行客户的数据不报送，存续业务中的所有个人信息都报送。。 | I10: 修改
D11: GRKHGXB | E11: 个人客户关系表 | F11: 202 | G11: 全量表，报送截止采集日有效的数据以及与上一采集日期间失效的数据。 | H11: 个人客户关系信息。所有的个人对个人的关系，包括担保、亲属、配偶等。对公客户为个人客户担保的关系也需在本表报送。本人为本人担保的关系不报送。 | I11: 修改
D12: DGKHXXB | E12: 对公客户信息表 | F12: 203 | G12: 全量表，报送截止采集日有效的数据以及与上一采集日期间失效的数据。 | H12: 银行机构所有对公客户的基本信息。集团类的虚拟客户的客户信息要上报，在法人代表一栏填集团客户。银行对企业分公司等非法人机构授信的，视同单一法人客户报送。以机构名义登记客户资料的个体工商户、私营业主应纳入本表填报范围。对于同业客户、政府机关、境外客户，若无法获取相关信息无法填报的数据项，允许为空。对于不再列为银行客户的数据不报送。 | I12: 修改
D13: DGKHCWXXB | E13: 对公客户财务信息表 | F13: 204 | G13: 增量表，报送本次采集日与上一采集日期间新增的数据。 | H13: 报送本月源系统中新收集的对公客户财务信息。对于非授信客户、负债类客户、离岸对公客户、机关事业单位、未达到税务部门建账标准的个体工商户等无需报送。 | I13: 新增
D14: JTKHB | E14: 集团客户表 | F14: 205 | G14: 全量表，报送截止采集日有效的数据以及与上一采集日期间失效的数据。 | H14: 报送在本行纳入集团授信的客户信息，包括供应链客户信息。以集团成员为最小粒度报送。同业集团客户信息无需报送。 | I14: 新增
D15: GLGXB | E15: 关联关系表 | F15: 206 | G15: 全量表，每期报送银行机构最新的客户关联关系信息，已失效的关联关系不报送。 | H15: 报送机构收集的对公客户以及填报机构自身的关联方和关系人信息，应包括主要股东、内部人、内部人近亲属、关联法人的董事、关联法人的监事、主要股东控股企业、内部人可施加重大影响的企业、供应链上下游、共同出资组建企业、担保关系、实际控制人、共同受同一关系人控制、集团成员、法定代表人、董事长（理事长）、监事长、总经理、财务主管等关联关系。对于填报机构自身的关联关系，需与机构自身认定的关联方和关系人一致，对于对公客户的关联关系，采取能采尽采的原则，包括但不限于授信尽职调查、外部数据源查询等途径获知的关联关系。同一关联方兼任或具有多重关联关系的，分多条进行报送。非授信客户、负债类客户不报送。 | I15: 修改
B16: 卡片信息 | C16: 003
D17: JJKXXB | E17: 借记卡信息表 | F17: 301 | G17: 全量表，报送截止采集日有效的数据以及与上一采集日期间失效的数据。 | H17: 个人和对公客户在银行机构开办的借记卡信息，指只能存取款而无法透支的卡片信息。本表需每月全量报送，当卡片状态为“注销”时，可在报送最后状态的次月不再报送。 | I17: 修改
D18: CZXXB | E18: 存折信息表 | F18: 302 | G18: 全量表，报送截止采集日有效的数据以及与上一采集日期间失效的数据。 | H18: 个人和对公客户在银行机构开办的存折信息。包括存折和存单。本表需每月全量报送，当存折状态为“注销”时，可在报送最后状态的次月不再报送。 | I18: 修改
D19: SDSHXXB | E19: 收单商户信息表 | F19: 303 | G19: 全量表，报送截止采集日有效的数据以及与上一采集日期间失效的数据。 | H19: 报送本行因线下线上收单业务而拓展的线下POS终端、线上终端以及二维码商户的信息。同一商户存在多个POS终端的，按多条报送。商户状态为“失效”或“注销”等状态的，在报送最后状态的次月可不再报送。 | I19: 新增
B20: 会计记账信息 | C20: 004
D21: ZZKJQKMB | E21: 总账会计全科目表 | F21: 401 | G21: 全量表，报送截止采集日有效的数据以及与上一采集日期间失效的数据。 | H21: 本表报送银行机构会计记账使用的所有会计科目及余额变动情况信息。余额为零的科目也要报送，不再使用的科目可以不报送。只报境内银行（不报子公司），包括总行、一级分行、二级分行、一级支行（最多报4级）。如果发生新老科目变更，在当期数据中报送最新科目即可。每月最后一天数据应同时报送按月和按日为周期的会计数据，每年最后一天数据应同时报送按日、按月、季、半年、年为周期的会计数据，以此类推。只报送人民币和本外币合计。 | I21: 修改
D22: NBKMDZB | E22: 内部科目对照表 | F22: 402 | G22: 全量表，报送截止采集日有效的数据以及与上一采集日期间失效的数据。 | H22: 本表报送总账会计全科目的上下级对应关系，以会计科目为最小粒度报送。内部科目对照表由法人机构统一确定，分支机构按同一内容报送。报送科目必须与当期《总账会计全科目表》中的科目一致。此表首次采集为全量采集，后续采集如有变化，需全量报送。 | I22: 修改
D23: GRHQCKFHZ | E23: 个人活期存款分户账 | F23: 403 | G23: 全量表，报送截止采集日有效的数据以及与上一采集日期间失效的数据。 | H23: 指金融机构吸收的所有以个人名义存入的活期存款。报送范围：参照1104报表G01_III中[2.2.1个人活期存款]除去信用卡溢缴款部分填报。个体工商户的存款属于个人存款。信用卡业务不在本表中填报。以活期存款账号为最小颗粒报送，如账户注销或终结，在报送该账户最终状态后的次月可不再报送。 | I23: 修改
D24: GRHQCKFHZMX | E24: 个人活期存款分户账明细记录 | F24: 404 | G24: 增量表，报送本次采集日与上一采集日期间新增的数据。 | H24: 除计息、扣利息税外，所有影响个人活期存款账户余额变动的交易信息，不包括查询交易。
D25: GRDQCKFHZ | E25: 个人定期存款分户账 | F25: 405 | G25: 全量表，报送截止采集日有效的数据以及与上一采集日期间失效的数据。 | H25: 个人客户在银行机构开设的除活期存款账户以外其他所有以个人名义划入的存款账户信息，包括定期、定活两便、通知存款、机构性存款等多种非活期的账户信息。报送范围：参照1104报表G01_III[2.2 个人存款]-[2.2.1 个人活期存款]口径填报。个体工商户的存款属于个人存款。信用卡业务不在本表中填报。以定期存款账号为最小颗粒报送，如账户注销或终结，在报送该账户最终状态后的次月可不再报送。 | I25: 修改
D26: GRDQCKFHZMX | E26: 个人定期存款分户账明细记录 | F26: 406 | G26: 增量表，报送本次采集日与上一采集日期间新增的数据。 | H26: 除计息、扣利息税外，所有影响个人定期存款账户余额变动的交易信息，不包括查询交易。
D27: DGHQCKFHZ | E27: 对公活期存款分户账 | F27: 407 | G27: 全量表，报送截止采集日有效的数据以及与上一采集日期间失效的数据。 | H27: 指银行机构吸收的除个人以外的机构（包括企业、事业单位、机关、社会团体、同业机构等）开立的所有活期存款账户信息。报送范围：参照1104报表G01_III中[2.1.1单位活期存款]以及财政部门、金融机构（同业）活期存款填报。按照人行账户管理办法划分标准，包括所有对公类活期账户余额（含同业账户）。以活期存款账号为最小颗粒报送，如账户注销或终结，在报送该账户最终状态后的次月可不再报送。 | I27: 修改
D28: DGHQCKFHZMX | E28: 对公活期存款分户账明细记录 | F28: 408 | G28: 增量表，报送本次采集日与上一采集日期间新增的数据。 | H28: 所有影响对公活期存款账户余额变动的交易信息，不包括查询交易。不包括计息和扣利息税记录。
D29: DGDQCKFHZ | E29: 对公定期存款分户账 | F29: 409 | G29: 全量表，报送截止采集日有效的数据以及与上一采集日期间失效的数据。 | H29: 指银行机构吸收的除个人以外的机构（包括企业、财政部门、社保基金、部队、住房公积金、社会团体、同业机构等）开立的，除活期存款以外的其他所有存款账户信息。报送范围：参照1104报表G01_III[2.1 单位存款] - [2.1.1单位活期存款] + 财政部门、金融机构除活期外存款。包括对公定期、定活两便，以及对公协议、协定、结构性存款、同业存放、吸收的保险公司存放款、社会保障基金、2009年1月1日前签署的邮政储蓄机构等的协议存款的定期存款分户账信息。以定期存款账号为最小颗粒报送，如账户注销或终结，在报送该账户最终状态后的次月可不再报送。 | I29: 修改
D30: DGDQCKFHZMX | E30: 对公定期存款分户账明细记录 | F30: 410 | G30: 增量表，报送本次采集日与上一采集日期间新增的数据。 | H30: 所有影响对公定期存款账户余额变动的交易信息，不包括查询交易。不包括计息和扣利息税记录。
D31: NBFHZ | E31: 内部分户账 | F31: 411 | G31: 全量表，报送截止采集日有效的数据以及与上一采集日期间失效的数据。 | H31: 根据会计核算科目，除机关财务账、单列账之外的科目原则上都归入内部账采集；单列账、机关财务账不报送，资本账户需要报送。以内部分户账号为最小颗粒报送，如账户注销或终结，在报送该账户最终状态后的次月可不再报送。交易与核算分离的机构，应根据总账科目中划分出对应内部分户账性质的科目，自定义内部分户账号进行报送。 | I31: 修改
D32: NBFHZMX | E32: 内部分户账明细记录 | F32: 412 | G32: 增量表，报送本次采集日与上一采集日期间新增的数据。 | H32: 根据会计核算科目，除机关财务账、单列账之外的科目原则上都归入内部账采集；机关财务账、单列账不需要在此表报送，报送至信用卡和其余六个对公/个人分户账中；资本账户需要报送。
D33: GRXDFHZ | E33: 个人信贷分户账 | F33: 413 | G33: 全量表，报送截止采集日有效的数据以及与上一采集日期间失效的数据。 | H33: 本表为开展各项表内、表外信贷业务，以个人名义在银行机构所开立的信贷账户信息。报送范围：1104报表G01_VII[2.21 个人贷款(不含个人经营性贷款)] + [4.个人经营性贷款] - [2.21.1信用卡] + G01_I_2《委托贷款投向统计表》[2.21个人贷款(不含个人经营性贷款)] 。个体工商户、私营业主以营业执照等证件开立的对公账户也计入本表。表内个人贷款不报送信用卡业务。表外业务只报送委托贷款（非现金管理项下），其他不报送。以信贷借据号为最小粒度报送，借据结清、核销或转让的，可在报送最后状态的次月不再报送。账户状态为“销户”时，也可于次月不再报送。 | I33: 修改
D34: GRXDFHZMX | E34: 个人信贷分户账明细记录 | F34: 414 | G34: 增量表，报送本次采集日与上一采集日期间新增的数据。 | H34: 所有影响个人信贷账户余额或利息变动的交易信息，包括还本、还息，不包括查询交易。贷款核销或者转让（包括资产证券化）也应该在本表体现：明细科目填报本金科目，交易金额为核销或转让前本金余额，余额为0，交易对手填写借款人自身信息，摘要中标明核销或者转让交易。 | I34: 修改
D35: DGXDFHZ | E35: 对公信贷分户账 | F35: 415 | G35: 全量表，报送截止采集日有效的数据以及与上一采集日期间失效的数据。 | H35: 除个人以外的各类机构（包括企业、机关团体、社保基金、部队、住房公积金）为开展各项信贷业务，在银行机构所开立的信贷账户信息。报送范围：1104报表G01_VII[1.各项贷款] - [2.21 个人贷款(不含个人经营性贷款)] - [4.个人经营性贷款] + G01_I_2《委托贷款投向统计表》[1.委托贷款合计（非现金管理项下）] - G01_I_2[2.21个人贷款(不含个人经营性贷款)]。表外业务只报送委托贷款（非现金管理项下），其他不报送。对于票据贴现和买断式转贴现，可以填报为信贷分户账号=信贷借据号=票据号码；对于其他若没有对应信贷分户账号的业务，可以填报为信贷分户账号=信贷借据号=业务编号。以信贷借据号为最小粒度报送，借据结清、核销或转让的，可在报送最后状态的次月不再报送。账户状态为“销户”时，也可于次月不再报送。 | I35: 修改
D36: DGXDFHZMX | E36: 对公信贷分户账明细记录 | F36: 416 | G36: 增量表，报送本次采集日与上一采集日期间新增的数据。 | H36: 所有影响对公信贷账户余额或利息变动的交易信息，包括还本、还息，不包括查询交易。贷款核销或者转让（包括资产证券化）也应该在本表体现：明细科目填报本金科目，交易金额为核销或转让前本金余额，余额为0，交易对手填写借款人自身信息，摘要中标明核销或者转让交易。 | I36: 修改
B37: 各项贷款 | C37: 005
D38: XDHTB | E38: 信贷合同表 | F38: 501 | G38: 全量表，报送截止采集日有效的数据以及与上一采集日期间失效的数据。 | H38: 报送范围：按照1104报表G01_VII[1.各项贷款] - G01_VII[2.21.1信用卡] + G01_I_2《委托贷款投向统计表》[1.委托贷款合计（非现金管理项下）]口径填报。报送个人贷款、对公贷款、票据贴现、买断式转贴现、贸易融资业务、融资租赁业务、委托贷款（非现金管理项下）对应的业务合同，以及各项垫款对应的原业务合同。委托贷款中现金管理项下委托贷款不报送，其他表外业务不报送。信用卡业务不报送。对于票据贴现和买断式转贴现，可以填报为信贷合同号=信贷借据号=票据号码；对于其他若没有对应合同号的业务，可以填报为信贷合同号=信贷借据号=业务编号。已撤销、失效、终结的合同在报送合同最后状态的次月可不再报送。 | I38: 修改
D39: GRXDYWJJB | E39: 个人信贷业务借据表 | F39: 502 | G39: 全量表，报送截止采集日有效的数据以及与上一采集日期间失效的数据。 | H39: 所有以个人名义在信贷业务中签订的借据信息。报送范围：按照1104报表G01_VII[2.21 个人贷款(不含个人经营性贷款)] + [4.个人经营性贷款] - [2.21.1信用卡] + G01_I_2《委托贷款投向统计表》[2.21个人贷款(不含个人经营性贷款)] 填报口径。委托贷款中现金管理项下委托贷款不报送，其他表外业务不报送。信用卡业务不报送。对于票据贴现和买断式转贴现，可以填报为信贷合同号=信贷借据号=票据号码；对于其他若没有对应借据号的业务，可以填报为信贷合同号=信贷借据号=业务编号。借据状态为结清、核销、转让的可在报送最后状态的次月不再报送。 | I39: 修改
D40: DGXDYWJJB | E40: 对公信贷业务借据表 | F40: 503 | G40: 全量表，报送截止采集日有效的数据以及与上一采集日期间失效的数据。 | H40: 所有以机构名义在信贷业务中签订的借据信息。报送范围：1104报表G01_VII[1.各项贷款] - [2.21 个人贷款(不含个人经营性贷款)] - [4.个人经营性贷款] + G01_I_2《委托贷款投向统计表》[1.委托贷款合计（非现金管理项下）] - G01_I_2[2.21个人贷款(不含个人经营性贷款)]。委托贷款中现金管理项下委托贷款不报送，其他表外业务不报送。对于票据贴现和买断式转贴现，可以填报为信贷合同号=信贷借据号=票据号码，信用证业务可填报信用证号；对于其他若没有对应借据号的业务，可以填报为信贷合同号=信贷借据号=业务编号。借据状态为结清、核销、转让的可在报送最后状态的次月不再报送。 | I40: 修改
D41: STZFXXB | E41: 受托支付信息表 | F41: 504 | G41: 增量表，报送上一采集日至当前采集日之间新增的信贷业务借据与受托支付对象的映射信息。 | H41: [个人信贷业务借据表]和[对公信贷业务借据表]中放款方式为“受托支付”或“混合支付”的，在该表中报送受托支付对象信息。 | I41: 新增
D42: XMDKXXB | E42: 项目贷款信息表 | F42: 505 | G42: 全量表，报送截止采集日有效的数据以及与上一采集日期间失效的数据。 | H42: 符合以下特征的贷款的相关信息：（一）贷款用途通常是用于建造一个或一组大型生产装置、基础设施、房地产项目或其他项目，包括对在建或已建项目的再融资；（二）借款人通常是为建设、经营该项目或为该项目融资而专门组建的企事业法人，包括主要从事该项目建设、经营或融资的既有企事业法人；（三）还款资金来源主要依赖该项目产生的销售收入、补贴收入或其他收入，一般不具备其他还款来源。以信贷借据号为最小颗粒报送，同一合同下多笔借据的按多条报送。已结清、核销的数据在次月不再报送。 | I42: 修改
D43: YTDKXXB | E43: 银团贷款信息表 | F43: 506 | G43: 全量表，报送截止采集日有效的数据以及与上一采集日期间失效的数据。 | H43: 银团贷款，不论本行是参贷行还是主办行，只报送本行的信贷合同，银团贷款内其他机构的信贷合同不录入本表，行内银团不在此表报送。以信贷借据号为最小颗粒报送，同一合同下多笔借据的按多条报送。如果主办行与参贷行与客户签订同一份信贷合同的，银团贷款内所有机构均需录入该信贷合同。已结清、核销的数据在次月不再报送。 | I43: 修改
D44: PJTXB | E44: 票据贴现表 | F44: 507 | G44: 全量表，报送截止采集日有效的数据以及与上一采集日期间失效的数据。 | H44: 报送本行经办的“票据直贴”业务的明细信息。报送范围：1104报表G01_Ⅲ中[1.3贴现及买断式转贴现]-[1.3.1其中:买断式转贴现]。票据状态为“卖断”、“解付”或“核销”的数据，在报送票据最后状态的次月可不再报送。 | I44: 新增
D45: PJZTXB | E45: 票据转贴现表 | F45: 508 | G45: 全量表，报送截止采集日有效的数据以及与上一采集日期间失效的数据。 | H45: 报送本行发生的转贴现买断、转贴现卖断、质押式回购正回购、质押式回购逆回购、买断式回购正回购、买断式回购逆回购、再贴现等业务的明细信息。票据状态为“卖断”、“解付”或“核销”的数据，在报送票据最后状态的次月可不再报送。 | I45: 新增
D46: MYRZYWB | E46: 贸易融资业务表 | F46: 509 | G46: 全量表，报送截止采集日有效的数据以及与上一采集日期间失效的数据。 | H46: 填报机构提供的各类与国际、国内贸易结算工具相关的融资或信用便利业务。报送范围：1104报表G01_Ⅲ中[1.4贸易融资]包含的业务明细。本行开出的保函及信用证在保函及信用证表中报送，不在本表中填报。贷款状态为结清、核销、转让的，于次月不再报送。 | I46: 修改
D47: RZZLYWB | E47: 融资租赁业务表 | F47: 510 | G47: 全量表，报送截止采集日有效的数据以及与上一采集日期间失效的数据。 | H47: 报送填报机构与租赁公司合作，购买承租人指定租赁物件，与承租人签订租赁合同，待合同期满后租赁物资产所有权转移给承租人的一类业务。报送范围：参照1104报表G01_III[1.5融资租赁]填报口径。贷款状态为结清、核销、转让的，可在报送最终状态的次月不再报送。 | I47: 新增
D48: DKDJB | E48: 垫款登记表 | F48: 511 | G48: 全量表，报送截止采集日有效的数据以及与上一采集日期间失效的数据。 | H48: 填报信用证、承兑汇票、保函、贵金属租赁等业务产生的各项垫款信息。报送范围：与1104报表G01_Ⅵ《各项垫款情况表》报送口径一致。垫款状态为“结清”、“转让”、“核销”的，在报送最后状态的次月可不再报送。 | I48: 新增
B49: 表内外担保信息 | C49: 006
D50: BNWYWDBHTB | E50: 表内外业务担保合同表 | F50: 601 | G50: 全量表，报送截止采集日有效的数据以及与上一采集日期间失效的数据。 | H50: 各项表内贷款及表外业务中所签订的各类担保合同信息，至少包括普通担保和最高额担保合同。以保证金形式的担保无需在本表填报，但以存单质押形式的担保需要填报。本表反映被担保合同和担保合同之间的关系，为多对多关系表，一个担保合同担保多个业务合同的，需按多笔填报，多个担保合同担保一个合同的，也需按多笔填报。失效的担保合同于次月不再报送。 | I50: 修改
D51: BNWYWDBR | E51: 表内外业务担保人 | F51: 602 | G51: 全量表，报送截止采集日有效的数据以及与上一采集日期间失效的数据。 | H51: 担保合同中约定的担保人信息。担保类型为抵押和质押的，担保人应填写抵质押物所有权人；担保类型为保证的，担保人应填写保证人。同一份担保合同有多个担保人的，每个担保人填写一条记录。失效担保合同的担保人于次月不再报送。 | I51: 修改
D52: BNWYWDZYW | E52: 表内外业务抵质押物 | F52: 603 | G52: 全量表，报送截止采集日有效的数据以及与上一采集日期间失效的数据。 | H52: 担保合同中约定的各类质押、抵押物信息。对于同一担保合同有不同的抵质押物的，需以不同的质或抵押物编号分多条记录报送。以保证金形式的押品无需在本表填报，但以存单质押形式的押品需要填报。失效担保合同的押品信息于次月不再报送。 | I52: 修改
B53: 信贷管理信息 | C53: 007
D54: SXXXB | E54: 授信信息表 | F54: 701 | G54: 全量表，报送截止采集日有效的数据以及与上一采集日期间失效的数据。 | H54: 对客户授信的信息，但不包含客户使用授信的信息。包括对公和个人、同业客户授信。个人授信额度包括个人贷款、准贷记卡透支额度和信用卡额度授信。对公和同业授信包括已经或预期可能由本行承担信用风险的各类产品额度，包含但不限于流动资金贷款、固定资产贷款、项目融资、贸易融资、透支、保理、票据、保函、信用证、债券投资、特定目的载体投资、买入返售、同业拆借、同业存款等产品额度。 1.按授信协议为最细颗粒填报，有授信的客户都需要报送，如低风险额度授信都需要填报授信信息。 2.表内、表外、代管理的信贷资产均需报送，如：本行信贷资产转让后由本行代管的授信信息仍需报送。 3.增加授信的，应该按照单笔报送。如发生授信额度变更的，填写最新的协议授信额度。 4.无授信的无需报送。 5.授信协议失效的，报送协议最后状态的次月不再报送。 | I54: 修改
D55: DKHXB | E55: 贷款核销表 | F55: 702 | G55: 全量表，报送截止采集日有效的数据以及与上一采集日期间失效的数据。 | H55: 个人信贷业务借据、对公信贷业务借据、信用卡信息表中已核销的贷款信息。 1.包含信用卡核销，信贷借据号填报为卡号，信贷合同号填报为信用卡账户号。 2.以信贷借据号或信用卡卡号为最小颗粒报送。 3.根据财政部2017年《金融企业呆账核销管理办法》规定，符合规定完全终结的信贷资产可以在报送次月后不再报送。通过各种手段处置已核销资产结清欠款或已无追索权的，也视为“完全终结”。 4.可以参考1104G12填报口径，不包含境外，但所有账销案存的贷款均需填报，与1104统计数据不作强制核对。 | I55: 修改
D56: DKZQB | E56: 贷款展期表 | F56: 703 | G56: 增量表，报送本次采集日与上一采集日期间新增的数据。 | H56: 所有表内信贷业务+委托贷款展期信息。不报送除委托贷款以外的表外业务。 | I56: 修改
D57: XDZCZRB | E57: 信贷资产转让表 | F57: 704 | G57: 全量表，报送截止采集日有效的数据以及与上一采集日期间失效的数据。 | H57: 业务范围：包含1104报表G34《信贷资产转让情况统计表》口径业务，但还包含转入的信贷资产。仅报送行外的转让，行内机构间的转让无需报送。票据的买卖、买入返售、卖出回购不在本表填报。含已核销贷款，本金按实际填写0即可。终结的转让合同在报送最后状态后不再报送。 | I57: 修改
D58: ZCZRGXB | E58: 资产转让关系表 | F58: 705 | G58: 增量表，报送本次采集日与上一采集日期间新增的数据。 | H58: 本表报送资产转让包含多张借据时，资产转让合同与的映射，以同一资产转让合同多条借据记录的方式报送。每月报送新增的转让合同于借据映射关系，已报送过的映射关系不再报送。本表报送行外的转让，行内机构间的转让不需报送。对于信用卡资产转让，以信用卡账号填报为借据号。票据的买卖、买入返售、卖出回购不在本表填报。 | I58: 修改
D59: DKWJXTBD | E59: 贷款五级形态变动表 | F59: 706 | G59: 增量表，报送本次采集日与上一采集日期间新增的数据。 | H59: 所有表内信贷+委托贷款的五级分类变动信息，与其他表格中五级分类字段一致。不报送除委托贷款以外的表外业务。无需报送新发放业务（五级分类从无到有）的五级形态变动。 | I59: 修改
B60: 信用卡 | C60: 008
D61: XYKXXB | E61: 信用卡信息表 | F61: 801 | G61: 全量表，报送截止采集日有效的数据以及与上一采集日期间失效的数据。 | H61: 除借记卡外的其他所有卡片的信息，包括信用卡、贷记卡、准贷记卡、公务卡等，以卡号为最小粒度报送。状态为“销户”的信用卡在报送最后状态的次月不再报送。状态为“销户”的账户以及账户下所属的所有信用卡在报送最后状态的次月不再报送。 | I61: 修改
D62: XYKJYMXB | E62: 信用卡交易明细表 | F62: 802 | G62: 增量表，报送本次采集日与上一采集日期间新增的数据。 | H62: 除借记卡外的其它所有卡片影响余额变动的交易明细，包括信用卡、贷记卡、准贷记卡、公务卡等，不包括查询交易，以信用卡号为最小粒度报送。 | I62: 修改
D63: XYKSXQKB | E63: 信用卡授信情况表 | F63: 803 | G63: 全量表，报送截止采集日有效的数据以及与上一采集日期间失效的数据。 | H63: 报送信用卡持卡人当月授信情况，报送范围：本表中[透支金额]数据项与1104报表G01_VII中[2.21.1信用卡]报送口径一致。客户额度按同一账户下的总额度报送，不以单张信用卡额度报送。对主副卡客户（一账户多个客户）的情况，本表只报送主卡人的授信信息。同一客户多个账户的，按多条分别报送。同一账户多个币种共享额度的，按记账币种统一折算填报。状态为“销户”的账户在报送最后状态的次月可不再报送。 | I63: 修改
D64: XYKFQYWB | E64: 信用卡分期业务表 | F64: 804 | G64: 增量表，报送本次采集日与上一采集日期间新增的数据。 | H64: 填报每月新增的持卡人分期业务情况。
B65: 人行金融机构资产负债项目报表 | C65: 009
D66: RHJRJGZCFZXMBB | E66: 人行金融机构资产负债项目报表 | F66: 901 | G66: 增量表，报送本次采集日与上一采集日期间新增的数据。 | H66: 报送人民银行的资产负债科目统计表数据，内容根据最新人行全科目上报情况上报。报送范围：仅报送总行法人、分行层级汇总报表，对于无对应机构的汇总报表（如XX市XX区汇总）无需报送。报送周期与报送人行周期一致，若当月无新增则无需报送。 | I66: 修改
B67: 表外授信业务 | C67: 010
D68: PJCPXXB | E68: 票据出票信息表 | F68: 1001 | G68: 全量表，报送截止采集日有效的数据以及与上一采集日期间失效的数据。 | H68: 报送由出票人签发并向填报机构申请，经填报机构承兑的汇票。报送范围：参照1104报表G01_I_1《表外业务情况表》[1.承兑汇票]填报口径。票据状态为卖断（转贴现卖断），解付（票据到期且出票人已付款）的数据，在报送票据最后状态的次月可不再报送。 | I68: 修改
D69: BHYXYZB | E69: 保函与信用证表 | F69: 1002 | G69: 全量表，报送截止采集日有效的数据以及与上一采集日期间失效的数据。 | H69: 报送本行开出的保函、信用证、购买协议等信息。报送范围：参照1104报表G01_I_1《表外业务情况表》中[2.跟单信用证]+[3.保函]+[4.信用风险仍在银行的销售与购买协议]+[5.其他担保类业务]填报口径，票据业务不在本表中报送。合同到期且已结清的数据，在报送合同最后状态的次月不再填报。 | I69: 新增
D70: MYBJXXB | E70: 贸易背景信息表 | F70: 1003 | G70: 增量表，报送本次采集日与上一采集日期间新增的数据。 | H70: 填报承兑汇票、保函、信用证、保理融资等业务为审查贸易背景真实性收集的发票、仓单、提单等信息，以能采尽采的原则，每月报送新收集的单据信息。报送范围：本行开出的票据（同《票据出票信息表》），本行开立的保函和信用证（同《保函与信用证表》），保理融资业务（同《贸易融资业务表》中的保理融资业务），其中非基于企业间贸易的保函可以不报送，业务尚未收集发票的暂时不报送。非本行开立的票据、保函、信用证的单据信息如未收集发票信息的可以不报送。同一票据或合同下对应的多个单据，以单据编号为最小粒度逐条报送。 | I70: 新增
D71: WTDKXXB | E71: 委托贷款信息表 | F71: 1004 | G71: 全量表，报送截止采集日有效的数据以及与上一采集日期间失效的数据。 | H71: 报送范围：参照1104报表G01_I_1[13.委托贷款]口径，报送所有个人及对公委托贷款业务，包括现金管理项下委托贷款、非现金管理项下委托贷款和公积金委托贷款。对于现金管理项下委托贷款，每发生一笔放款仅报送一次，以后不再报送，贷款状态以“其他-现金管理项下”报送。结清或者终结的委托贷款，在报送合同最后状态的次月不再填报。 | I71: 修改
D72: DLDJYXXB | E72: 代理代销交易信息表 | F72: 1005 | G72: 增量表，报送本次采集日与上一采集日期间新增的数据。 | H72: 报送范围：参照1104报表G01_I中[15.代理代销业务]填报口径。填报在阶段开始日到结束日之间，银行新做的代理代销业务。根据G01_I[15.7其他]口径，代理销售他行发行的理财产品也需要报送，包括填报机构理财子公司发行的理财产品。涉及分红、付息等交易无需报送。涉及赎回、卖出的交易需要报送。 | I72: 新增
D73: DKZJJYXXB | E73: 代客资金交易信息表 | F73: 1006 | G73: 增量表，报送本次采集日与上一采集日期间新增的数据。 | H73: 填报在阶段开始日到结束日之间，银行做的代客资金交易信息。包括代客结售汇、代客衍生品交易及其他代客资金交易业务。对于衍生品交易，涉及远期交易的仅在合同签订时报送一笔远端交易信息，交割时不必报送，但代客平盘交易需要按照单笔报送。对于掉期类衍生品交易仅需填报远端交易。债券承销，以及代销信托、资管计划、基金、贵金属等填报至代理代销信息表中。自营资金不报送在本表。 | I73: 新增
B74: 自营资金交易信息 | C74: 011
D75: HLXXB | E75: 汇率信息表 | F75: 1101 | G75: 增量表，报送本次采集日与上一采集日期间新增的数据。 | H75: 国家外汇管理局公布汇率的主要币种，填报各主要外币与人民币的折算汇率。其他货币对人民币的折算汇率，以当天美元兑人民币的基准汇率与同一天国际外汇市场其他货币兑美元汇率套算确定。机构可只填报常见的外币信息，但至少应包含其它表中填报使用过的所有外币。
D76: JRGJXXB | E76: 金融工具信息表 | F76: 1102 | G76: 全量表，报送截止采集日有效的数据以及与上一采集日期间失效的数据。 | H76: 记录[自营资金交易信息表]和[自营资金业务余额表]中所有业务对应的标的物，如债券、非标准化债权类资产、金融衍生品工具，已结清（余额为0）/赎回/终结的业务在报送最后状态的次月不再报送。同业往来大类下的同业存单，债券和同业投资大类下的所有业务需填报基础资产相关信息，基础资产如果对应多个的话，按多条报送。票据业务不在本表报送。 | I76: 修改
D77: ZYZJJYXXB | E77: 自营资金交易信息表 | F77: 1103 | G77: 增量表，报送本次采集日与上一采集日期间新增的数据。 | H77: 填报在阶段开始日到结束日之间，银行发生的自营资金交易，业务范围参考《自营报送范围》，其中债券与同业投资部分填报口径与1104报表G31一致。同一金融工具当月发生当月结清的数据也需要报送，买入与卖出操作按不同笔次分别填报。票据业务（包含贴现和转贴现）不在本表填报。对于衍生品交易，合约交易与实物交割应该分别填报，交割时按合约规定交易物的即期交易报送，涉及远期、掉期的合约交易仅报送一笔远端信息。同业往来大类下的同业存放业务在对公存款分户账及分户账明细报表中报送，不在本表报送。
D78: ZYZJYWYEB | E78: 自营资金业务余额表 | F78: 1104 | G78: 全量表，报送截止采集日有效的数据以及与上一采集日期间失效的数据。 | H78: 填报截止报送日期有余额的自营资金业务及所持有的头寸信息，业务范围参考《自营报送范围》，其中债券与同业投资部分余额填报口径与1104报表G31一致。票据业务（包含贴现和转贴现）不在本表填报。已结清（余额为0）/赎回/核销/终结的业务在报送最后状态的次月不再报送。同一金融工具当月发生当月结清的数据也需要一条，并于次月不再报送。
B79: 理财业务 | C79: 012
D80: LCCPXXB | E80: 理财产品信息表 | F80: 1201 | G80: 全量表，报送截止采集日有效的数据以及与上一采集日期间失效的数据。 | H80: 该表体现截至统计时点所有在全国银行业理财信息登记系统中取得产品登记编码并成功发行的理财产品相关信息。
D81: LCCPZTB | E81: 理财产品状态表 | F81: 1202 | G81: 全量表，报送截止采集日有效的数据以及与上一采集日期间失效的数据。 | H81: 该表体现统计期末存续的理财产品状态信息。
D82: LCCPDCCCXXB | E82: 理财产品底层持仓信息表 | F82: 1203 | G82: 全量表，报送截止采集日有效的数据以及与上一采集日期间失效的数据。 | H82: 该表体现统计期末理财产品持有所有类别资产的相关信息。
D83: FBZCMXXXB | E83: 非标资产明细信息表 | F83: 1204 | G83: 全量表，报送截止采集日有效的数据以及与上一采集日期间失效的数据。 | H83: 该表体现统计期末理财产品持有的非标准化债权类资产（目前包含信托贷款、委托贷款、信贷资产转让、收/受益权、委托债权、应收账款、带回购条款的股权性融资、债券融资类产品）明细信息。
D84: QTFBZCMXXXB | E84: 其他非标资产明细信息表 | F84: 1205 | G84: 全量表，报送截止采集日有效的数据以及与上一采集日期间失效的数据。 | H84: 该表体现统计期末理财产品持有的其他非标准化债权类资产（包括但不限于保理、融资租赁、股票质押融资等）明细信息。
D85: LCCPZCJYXXB | E85: 理财产品资产交易信息表 | F85: 1206 | G85: 增量表，报送本次采集日与上一采集日期间新增的数据。 | H85: 该表体现统计期内理财产品发生的逐笔投资交易信息。
D86: LCCPXSMXB | E86: 理财产品销售明细表 | F86: 1207 | G86: 增量表，报送上一采集日期至当前采集日期之间发生的本行理财产品交易信息。 | H86: 代销他行理财产品由银行机构在代理代销信息表中报送。 | I86: 修改
D87: KHLCZHXXB | E87: 客户理财账户信息表 | F87: 1208 | G87: 全量表，报送截止采集日有效的数据以及与上一采集日期间失效的数据。 | H87: 本行客户开立的理财分户账信息，报送本行理财产品账户信息，代销他行理财在他行数据源下报送。买入不同理财产品的，每个产品作为一条记录。如不设置理财账户的，对应填报其他相关信息。本表为状态表，每月逐客户（理财账号）、逐产品报送月底账户信息，若同一客户月内多次购买同一产品则将金额加总后作为一条记录。 | I87: 新增

Sheet 数据元说明
A2: 数据元说明
A4: 分类 | B4: 数据元编码 | C4: 数据元名称 | D4: 数据元英文 | E4: 数据元说明 | F4: 格式
A6: 公共信息 | B6: 001
B7: 001001 | C7: 名称 | D7: Name | E7: 名称应与公章所使用的名称完全一致。银行机构以银保监会金融机构许可证登记名称为准。无独立金融机构许可证的机构，可在本名称中体现出机构特征。第三方支付平台填报第三方支付平台名称。 客户名称按照客户的不同类型按如下标准填报。 （1）集团客户，填报银行对该集团授信采用的集团客户名称。视同集团客户填报的供应链融资填报核心企业客户名称。 （2）单一法人客户，经有关部门批准正式使用的全称，与公章所使用的名称完全一致。视同单一法人客户填报的分公司，填报分公司全称，与分公司公章所使用的名称完全一致。客户是境内涉密机构的，客户名称填报为“*********”。 （3）同业客户，经有关部门批准正式使用的客户全称，与客户公章所使用的名称完全一致。 （4）自然人，与有效证件上的姓名一致。 （5）境外客户，客户名称应尽量以中文翻译填报，如没有可填报英文名称。 | F7: C..400
B8: 001002 | C8: 是否标志 | D8: Yes or No | E8: 是，否。 | F8: C3
B9: 001003 | C9: 比例 | D9: Ratio | E9: 百分比为单位，即1/100，保留两位小数。如4.5%则填报为4.50。 | F9: D20.2
B10: 001004 | C10: 比例（精） | D10: Accurate rate | E10: 百分比为单位，即1/100，保留六位小数。4.123456%则填报为4.123456。 | F10: D20.6
B11: 001005 | C11: 日期 | D11: Date | E11: YYYYMMDD，默认值99991231。 | F11: C8
B12: 001006 | C12: 年月 | D12: Year & Month | E12: YYYYMM，默认值999912。 | F12: C6
B13: 001007 | C13: 时间 | D13: Time | E13: 24小时制时间，精确到秒。hhmmss，默认值000000。 | F13: C6
B14: 001008 | C14: 地址 | D14: Address | E14: 中文描述。个人填报个人住址。机构填报有关部门批准的有效证件上登记的地址。参照《企业法人营业执照》中的注册地填报，要写明省（区、市）、地（区、市、州、盟）、县（区、市、旗）。境外机构及境内涉密机构不填报。 | F14: C..400
B15: 001009 | C15: 电话 | D15: Tel. | E15: 手机号码或者区号-固定电话号码。 | F15: C..30
B16: 001010 | C16: 银行机构代码 | D16: Bank code | E16: 12位人行支付行号或SWIFT行号。 | F16: C..30
B17: 001011 | C17: 金融许可证号 | D17: Financial license number | E17: 金融许可证机构编码编制规则（试行） 一、机构编码结构 机构编码由大写英文字母和数字组成，共15位。分六个部分，分别是机构类型代码、机构代码、组织类别代码、发证机关代码、地址代码、顺序代码，从左至右顺序排列，如下表所示。 二、机构编码含义 （一）第［一］位是机构类型代码，用大写英文字母表示。 A-政策性银行 B-商业银行 C-农村合作银行 D-城市信用社 E-农村信用社 F-资金互助社 J-金融资产管理公司 K-信托公司 L-财务公司 M-金融租赁公司 N-汽车金融公司 P-货币经纪公司 Q-贷款公司 Z-其他类金融机构 新增机构类型时，根据需要确定机构类型代码。 （二）第［二］位至第［五］位是机构代码，用数字表示。 1.每个法人机构指定唯一的代码，由计算机系统按照规则自动生成。除农村信用社、资金互助社、贷款公司（E、F、Q类机构）外，全国统一编码。E、F、Q类机构在省（自治区、直辖市）范围内统一编码。 2.新设立的机构依照所属机构类型顺序排列。 机构代码编码示例如下： A-政策性银行 0001-国家开发银行 …… B-商业银行 0001-中国工商银行股份有限公司 …… C-农村合作银行 0001-天津大港农村合作银行 …… D-城市信用社 0001-邯郸市城市信用社股份有限公司 …… E-农村信用社天津市 0001-天津市宝坻区农村信用合作联社 …… 新疆维吾尔自治区 0001-新疆维吾尔自治区农村信用社联合社 …… F-资金互助社 吉林省 0001-吉林省梨树县闰家村百信农村资金互助社 …… 青海省 0001-青海省乐都县雨润镇兴乐农村资金互助社 …… J-金融资产管理公司 0001-中国华融资产管理公司 …… K-信托投资公司 0001-中诚信托投资有限责任公司 …… L-财务公司 0001-中海石油财务有限责任公司 …… M-金融租赁公司 0001-中国外贸金融租赁公司 …… N-汽车金融公司 0001-大众汽车金融（中国）有限公司 …… P-货币经纪公司 0001-上海国利货币经纪有限公司 …… Q-贷款公司四川省 0001-四川省仪陇县惠民贷款有限责任公司 …… 新疆维吾尔自治区 0001- …… Z-其他类金融机构 0001-中央国债登记结算有限责任公司 …… （三）第〔六〕位是组织类别代码，用大写英文字母表示。 机构类型不同，组织类别代码的含义不同。定义如下： 1.A-政策性银行 H-总行 G-总行营业部 H-级分行 K-一级分行营业部 M-二级分行 S-支行 X-其他分支机构 2.B-商业银行 H-总行 G-总行营业部、专营机构 B-一级分行 K-一级分行营业部 L-二级分行 M-直属支行 N-二级分行营业部 S-支行 U-分理处、办事处、营业所 V-储蓄所 X-其他分支机构 3.C-农村合作银行 H-总行 S-支行 U-分理处 V-储蓄所 X-其他分支机构 4.D-城市信用社 H-法人 S-分社、营业部 X-其他分支机构 5.E-农村信用社 H-省（自治区、直辖市）联合社 B-地（市）联合社、联社 S-县（市）联合社、联社、合作社（县级） T-信用合作社 U-信用社、分社 V-储蓄所 X-其他分支机构 6.F-资金互助社 H-法人 7.J-金融资产管理公司 H-总公司 B-办事处 X-其他分支机构 8.K-信托公司 H-法人 9.N-汽车金融公司 H-法人 10.L-财务公司 H-总公司 B-分公司 X-其他分支机构 11.M-金融租赁公司 H-总公司 B-分公司 X-其他分支机构 12.P-货币经纪公司 H-总公司 B-分公司 X-其他分支机构 13.Q-贷款公司 H-总公司 B-分公司 X-其他分支机构 14.Z-其他类金融机构 Z类机构组织类别代码编码方法参照以上规则。 新增机构类型时，参照以上规则，根据实际情况定义其组织类别代码。 （四）第〔七〕位是发证机关代码，用数字表示。 1-银保监会 2-银监局 3-银监分局 （五）第〔八〕位至第〔十一〕是地址代码，用数字表示。按照《中华人民共和国行政区划代码》 （GB/T2260），取市（地区、自治州、盟）、直辖市行政区划代码前四位，作为地址代码。 地址代码示例如下：1100表示北京市，1200表示天津市，1301表示石家庄市，…… （六）第〔十二〕位至第〔十五〕位是顺序代码，用数字表示。机构类型代码、机构代码、组织类别代码、发证机关代码和地址代码相同的机构按照制发金融许可证的顺序编码。 三、机构编码的编制规则 编制机构编码时，按照从左至右的顺序依次确定机构类型代码、机构代码、组织类别代码、发证机关代码、地址代码、顺序代码，由计算机自动生成。 为了保证机构编码的唯一性，以利于电子计算机较长时间地存储数据，因行政许可变更需换发金融许可证，涉及机构编码变更的，原机构编码不再使用.金融机构终止的，机构编码不再使用。注销开业许可收回金融许可证的，机构编码不再使用。 | F17: C..30
B18: 001012 | C18: 内部机构号 | D18: Inner organization number | E18: 银行内部机构号。应具有标识机构的唯一性。 | F18: C..30
... B46: 001040 | C46: 备注 | D46: Remark | E46: 银行自定义。 | F46: C..600
A47: 客户信息 | B47: 002
B48: 002001 | C48: 客户统一编号 | D48: Customer number | E48: 银行自定义的唯一识别客户的标识。供应链融资的填写供应链融资编码。 | F48: C..60
B49: 002002 | C49: 证件类别 | D49: Document type | E49: 同业客户：银行机构代码，金融许可证号，SWIFT编码，其他-XX。 对公客户：统一社会信用代码，组织机构代码，营业执照（工商注册号），公司注册证书，全球法人识别码，其他-XX。 个人客户：居民身份证，军官证，文职干部证，警官证，士兵证，户口簿，临时身份证，其他有效通行旅行证件，护照，学生证，无证件，其他-XX。 无法以枚举类型填报的，以“其他-XX”报送，其中“XX”为银行自定义类型。 对公客户优先填报统一社会信用代码，没有统一社会信用代码的对公客户填报组织机构代码。组织机构代码、统一社会信用代码均没有的可以填报客户提供的批文文号、开户主证件、上级机构统一社会信用代码等，以“其他-XX”填报。 | F49: C..60
B50: 002003 | C50: 证件号码 | D50: Document number | E50: 与证件类别对应的证件号码。涉及个人身份证件时需按照本规范给定规则进行脱敏处理。 | F50: C..70
B51: 002004 | C51: 国籍 | D51: Nationality | E51: 参照《GB/T 2659-2000 世界各国和地区名称》，填报中文名称。 | F51: C..60
B52: 002005 | C52: 民族 | D52: Ethnicity | E52: 国家认可的在公安户籍管理部门正式登记注册的客户所属民族的名称。 | F52: C..30
B53: 002006 | C53: 性别 | D53: Gender | E53: 男，女。 | F53: C3
B54: 002007 | C54: 学历 | D54: Education degree | E54: 参照《GB/T 4658-2006 学历代码》填写中文描述或中文字典。 | F54: C..30
B55: 002008 | C55: 职业 | D55: Career | E55: 中文描述或中文字典，银行自定义。 | F55: C..80
B56: 002009 | C56: 婚姻情况 | D56: Marriage | E56: 未婚，已婚，初婚，再婚，复婚，丧偶，离异。 | F56: C..6
B57: 002010 | C57: 上黑名单原因 | D57: Reason of on black list | E57: 中文字典或中文描述，银行自定义。 | F57: C..400
B58: 002011 | C58: 单位性质 | D58: Unit property | E58: 国有企业、民营企业、政府机关、事业单位、社会团体、境外机构、其他-银行自定义。无法以枚举类型填报的，以“其他-XX”填报，其中“XX”为银行自定义类型。 | F58: C..60
B59: 002012 | C59: 社会关系 | D59: Social relationship | E59: 配偶，父母，子女，亲属关系，朋友，同事，合作伙伴，离异原配偶，其他-银行自定义。无法以枚举类型填报的，以“其他-XX”填报，其中“XX”为银行自定义类型。 | F59: C..60
... B75: 002028 | C75: 财务报表编号 | D75: Financial statement number | E75: 唯一标识财务报表的编号，银行自定义。 | F75: C..30
A76: 账户 | B76: 003
B77: 003001 | C77: 账号 | D77: Account number | E77: 系统内最细一级的账号，无唯一性约束，不需要和序号、子序号等做拼接。 | F77: C..60
B78: 003002 | C78: 会计科目编号 | D78: Subject number of general ledger accounting | E78: 机构实际使用的总账会计科目编码。 | F78: C..200
B79: 003003 | C79: 会计科目名称 | D79: Subject name of general ledger accounting | E79: 机构实际使用的总账会计科目编码对应的名称。 | F79: C..200
B80: 003004 | C80: 会计科目级次 | D80: Subject grade of general ledger accounting | E80: 总账会计科目编号在科目结构中所对应的级次。 | F80: I..2
B81: 003005 | C81: 会计科目大类 | D81: Account category | E81: 资产、负债、所有者权益、损益、资产负债共同类、表外、其他。 | F81: C..30
B82: 003006 | C82: 会计科目子类 | D82: Account sub category | E82: 资产类业务子类：1现金，2贵金属，3存放中央银行款项，4存放同业款项，5应收利息，6贷款，7贸易融资，8贴现及买断式转贴现，9其他贷款，10拆放同业，11其他应收款，12投资，13买入返售资产，14长期待摊费用，15固定资产原价，16减：累计折旧，17固定资产净值，18固定资产清理，19在建工程，20无形资产，21抵债资产，22递延所得税资产，23其他资产，24各项资产减值损失准备。 负债类业务子类：25单位存款，26储蓄存款，27向中央银行借款，28同业存放款项，29同业拆入，30卖出回购款项，31汇出汇款，32应解汇款，33存入保证金，34应付利息，35应交税费，36应付职工薪酬，37应付福利费，38应付股利，39其他应付款，40预提费用，41递延收益，42预计负债，43转贷款资金，44应付债券，45其他负债，46递延所得税负债。 所有者权益类业务子类：47实收资本，48资本公积，49盈余公积，50一般风险准备，51信托赔偿准备，52未分配利润，53其他综合收益，54其他权益工具。 损益类业务子类：55利息收入，56利息支出，57手续费及佣金收入，58手续费及佣金支出，59投资损益，60公允价值变动损益，61汇兑损益，62资产处置损益，63其他业务收入，64营业支出，65营业外收入，66营业外支出，67资产减值损失，68所得税，69少数股东损益。 表外业务类别：70承兑汇票，71跟单信用证，72保函，73信用风险仍在银行的销售与购买协议，74其他担保类业务，75可随时无条件撤销的贷款承诺，76不可无条件撤销的贷款承诺，77未使用的信用卡授信额度，78其他承诺，79发行非保本理财产品，80委托贷款，81委托投资，82代理代销业务，83资产托管，84其他金融资产服务业务，85金融衍生品类。 | F82: C..200
B83: 003007 | C83: 统计科目编号 | D83: Statistic subject number | E83: 参照《中国人民银行关于建立金融基础数据统计制度的通知》（银发[2020]164号）中的统计指标编码填报。如： 单位存款：单位活期存款-12MG4/22MG4；单位定期存款-12MGB/22MGB；单位通知存款-12MGI/22MGI；单位协议存款-12MGR/22MGR；单位协定存款-12MH4/22MH4；单位保证金存款-12MHB/22MHB；单位结构性存款-12MHI/22MHI 个人存款：个人活期存款-12MI2/22MI2；个人定期存款-12MI4/22MI4；个人定活两便存款-12MI6/22MI6；个人通知存款-12MI8/22MI8；个人协议存款是A1411/2411 12MIA/22MIA ；个人协定存款-12MIC/22MIC；个人保证金存款-12MIE/22MIE；个人结构性存款-12MIG/22MIG 普通贷款：单位经营贷款-12M3H/22M3H；单位固定资产贷款-12M3I/22M3I；个人贷款-12M36/22M36；对非居民贷款-12M4E/22M4E ；单位经营贷款-12M5C/22M5C ；单位固定资产贷款-12M5D/22M5D；一般委托贷款-34R03 | F83: C..20
B84: 003008 | C84: 统计科目名称 | D84: Statistic subject name | E84: 参照《中国人民银行关于建立金融基础数据统计制度的通知》（银发[2020]164号）中的统计指标名称填报。如： 单位存款：单位活期存款-12MG4/22MG4；单位定期存款-12MGB/22MGB；单位通知存款-12MGI/22MGI；单位协议存款-12MGR/22MGR；单位协定存款-12MH4/22MH4；单位保证金存款-12MHB/22MHB；单位结构性存款-12MHI/22MHI 个人存款：个人活期存款-12MI2/22MI2；个人定期存款-12MI4/22MI4；个人定活两便存款-12MI6/22MI6；个人通知存款-12MI8/22MI8；个人协议存款是A1411/2411 12MIA/22MIA ；个人协定存款-12MIC/22MIC；个人保证金存款-12MIE/22MIE；个人结构性存款-12MIG/22MIG 普通贷款：单位经营贷款-12M3H/22M3H；单位固定资产贷款-12M3I/22M3I；个人贷款-12M36/22M36；对非居民贷款-12M4E/22M4E ；单位经营贷款-12M5C/22M5C ；单位固定资产贷款-12M5D/22M5D；一般委托贷款-34R03 | F84: C..120
B85: 003009 | C85: 借贷标志 | D85: D.C. flag | E85: 借，贷，借贷并列。 | F85: C..12
B86: 003010 | C86: 金额 | D86: Amount | E86: 与币种相对应金额。 | F86: D20.2
B87: 003011 | C87: 余额 | D87: Balance | E87: 与币种相对应金额。 | F87: D20.2
B88: 003012 | C88: 手续费 | D88: Commission | E88: 与币种相对应金额。 | F88: D20.2
... B108: 003032 | C108: 外部账号 | D108: Outer account number | E108: 外部转账交易使用的账号。银行个人账户报送跟个人内部账号相对应的外部卡号、折号、单号或客户账号。对公活期账户报送活期存款账户对应的客户账号，对公定期报送与该业务绑定交易的客户账号。第三方平台账户报送第三方平台实际支付的账号。 | F108: C..60
A109: 交易流水信息 | B109: 004
B110: 004001 | C110: 交易序列号 | D110: Trading time stamp | E110: 唯一标识该笔交易的编号，银行自定义。可以是业务编号，也可以是交易系统中使用的时间戳，如：时间戳(纳秒)：1530027865231834600。 | F110: C..100
B111: 004002 | C111: 交易类型 | D111: Trading type | E111: 转账，取现，存现，消费，代发，代扣，代缴，结息，批量交易，贷款发放，还款-还本，还款-还息，银证业务，投资理财，其他-银行自定义类型。无法以枚举类型填报的，以“其他-XX”报送，其中“XX”为银行自定义类型。 | F111: C..60
B112: 004003 | C112: 交易渠道 | D112: Trading channel | E112: 柜面，ATM，VTM，POS，网银，手机银行，银联交易，三方支付-银行自定义，其他-银行自定义。交易类型为三方支付的，以“三方支付-XX”填报，其中“XX”为第三方支付平台名称。如无法以枚举类型填报，则以“其他-XX”填报，其中“XX”为银行自定义类型。 | F112: C..60
B113: 004004 | C113: 现转标志 | D113: Cash or transfer | E113: 现，转。 | F113: C3
B114: 004005 | C114: 摘要 | D114: Memo | E114: 银行自定义交易内容的简要描述。可以是转账凭证上的备注、附言。 | F114: C..400
B115: 004006 | C115: 冲补抹标志 | D115: Regular， strike， mend | E115: 正常，冲补抹。 | F115: C..9
B116: 004007 | C116: 卡片交易类型 | D116: Card trading type | E116: 现金交易，还款交易，消费交易，转账交易，其他-银行自定义。以枚举类型填报，如无法以枚举类型填报，则以“其他-XX”填报，其中“XX”为银行自定义类型。 | F116: C..60
B117: 004008 | C117: 主要担保类型 | D117: Main guarantee type | E117: 质押，抵押，保证，信用。 | F117: C6
B118: 004009 | C118: 担保说明 | D118: Guarantee illustration | E118: 中文字典或中文描述，银行自定义。 | F118: C..400
A119: 授信交易信息 | B119: 005
B120: 005001 | C120: 产品名称 | D120: Product name | E120: 银行内部产品中文名称，银行自定义。 | F120: C..200
B121: 005002 | C121: 合同名称 | D121: Contract name | E121: 信贷合同的中文名称，银行自定义。 | F121: C..200
B122: 005003 | C122: 信贷业务种类 | D122: Loan business type | E122: 流动资金贷款，法人账户透支，项目贷款，项目贷款（银团），一般固定资产贷款，住房按揭贷款，商用房贷款，汽车贷款，互联网贷款，助学贷款，消费贷款，个人经营性贷款，票据贴现，买断式转贴现，贸易融资业务，融资租赁业务，垫款，委托贷款，其他-银行自定义类型。以枚举类型填报，如无法以枚举类型填报，则以“其他-XX”填报，其中“XX”为银行自定义类型。 | F122: C..100
B123: 005004 | C123: 利率浮动 | D123: Rate float | E123: 基准点为单位。浮动比例与上浮比例均折算点数填报。如上浮1%是填100.00，下浮1%是填-100.00，精确到小数点后2位。如果利率类型是固定利率，则利率浮动填写0.00。如利率类型是浮动利率，则与利率基准结合进行计算。 | F123: D8.5
B124: 005005 | C124: 主要担保方式 | D124: Main guarantee way | E124: 质押（含保证金），抵押，保证，信用，其他。 | F124: C..30
B125: 005006 | C125: 放款方式 | D125: Distribute way | E125: 自主支付，受托支付，混合支付，其他-银行自定义。以枚举类型填报，如无法以枚举类型填报，则以“其他-XX”填报，其中“XX”为银行自定义方式。 | F125: C..30
B126: 005007 | C126: 贷款用途 | D126: Loan purpose | E126: 贷款使用的具体内容。 | F126: C..1000
B127: 005008 | C127: 贷款投向行业 | D127: Invest industry | E127: 与1104报表G01_VII《贷款分行业情况表》口径一致，使用以下枚举值填报（序号+名称）：2.1农、林、牧、渔业；2.2采矿业；2.3制造业；2.4电力、热力、燃气及水的生产和供应业；2.5建筑业；2.6批发和零售业；2.7交通运输、仓储和邮政业；2.8住宿和餐饮业；2.9信息传输、软件和信息技术服务业；2.10金融业；2.11房地产业；2.12租赁和商务服务业；2.13科学研究和技术服务业；2.14水利、环境和公共设施管理业；2.15居民服务、修理和其他服务业；2.16教育；2.17卫生和社会工作；2.18文化、体育和娱乐业；2.19公共管理、社会保障和社会组织；2.20国际组织；2.21.1个人贷款-信用卡；2.21.2个人贷款-汽车；2.21.3个人贷款-住房按揭贷款；2.21.4个人贷款-其他；2.22买断式转贴现；2.23买断其他票据类资产；3.对境外贷款。 | F127: C..100
B128: 005009 | C128: 项目名称 | D128: Project name | E128: 项目贷款名称。 | F128: C..100
B129: 005010 | C129: 项目类型 | D129: Project type | E129: 基础设施建设项目，房地产项目，技术改造项目，科技开发项目，并购贷款，其他-银行自定义类型。如无法以枚举类型填报，则以“其他-XX”填报，其中“XX”为银行自定义类型。 | F129: C..100
B130: 005011 | C130: 批文文号 | D130: Approval number | E130: 银行自定义。 | F130: C..60
B131: 005012 | C131: 立项批文 | D131: Project approval | E131: 批文名称，可银行自定义。 | F131: C..60
... B171: 005052 | C171: 贸易内容 | D171: Trade content | E171: 贸易交易内容、货品或服务的简述信息，银行自定义。 | F171: C..600
A172: 卡片信息 | B172: 006
B173: 006001 | C173: 卡号 | D173: Card number | E173: 卡号，可以是借记卡号，贷记卡号等。 | F173: C..60
B174: 006002 | C174: 借记卡产品名称 | D174: Debit card name | E174: 借记卡产品名称，中文字典或中文描述，银行自定义。 | F174: C..200
B175: 006003 | C175: 卡片状态 | D175: Card state | E175: 未激活，正常，注销，冻结，睡眠，挂失，其他-银行自定义。以枚举类型填报，如果无法以枚举类型填报的，以“其他-XX”填报，其中XX为银行自定义的卡片状态。 | F175: C..30
B176: 006004 | C176: 存折类型 | D176: Passbook type | E176: 普通存折，存单，一本通，大额定期存单，其他-银行自定义。无法以枚举类型填报的，以“其他-XX”填报，其中XX为银行自定义的类型。 | F176: C..20
B177: 006005 | C177: 存折状态 | D177: Passbook state | E177: 未激活，正常，注销，冻结，睡眠，挂失，其他-银行自定义。无法以枚举类型填报的，以“其他-XX”填报，其中XX为银行自定义状态。 | F177: C..30
B178: 006006 | C178: 卡片名称 | D178: Card name | E178: 信用卡片种类名称。 | F178: C..60
B179: 006007 | C179: 卡片级别 | D179: Card level | E179: 中文字典或中文描述，银行自定义。 | F179: C..60
B180: 006008 | C180: 发卡渠道 | D180: Card issuing | E180: 银行网点、银行卡中心直销、银行官方网站（含网银渠道）、手机终端（银行APP）、合作发卡、第三方机构引流、其他-银行自定义。无法以枚举类型填报的，以“其他-XX”填报，其中XX为银行自定义类型。 | F180: C..60
B181: 006009 | C181: 商户编号 | D181: Merchant ID | E181: 唯一识别商户的编码。可以是商业银行自有商户编号，也可以是第三方支付机构收单交易显示的商户编号。 | F181: C..200
B182: 006010 | C182: 商户名称 | D182: Merchant Name | E182: 商户注册登记的名称。 | F182: C..400
B183: 006011 | C183: 商户MCC码 | D183: MCC Code | E183: 商户类别码。由四位数字代码组成。 | F183: C4
B184: 006012 | C184: 商户MCC名称 | D184: MCC Name | E184: 商户类别码对应的名称。 | F184: C..400
... B189: 006017 | C189: 清算账号类型 | D189: Banding account type | E189: 本行卡，本行对公结算账户，他行卡，他行对公结算账户，第三方平台账户-银行自定义。清算账号为第三方平台账户的，需填报至具体平台名称。 | F189: C..30
A190: 信贷管理信息 | B190: 007
B191: 007001 | C191: 授信协议号 | D191: Credit agreement number | E191: 填报银行授予客户授信额度的授信号码（或授信合同号码），该号码唯一标识该笔授信。若银行对该客户有多笔授信，应逐笔填列。 | F191: C..60
B192: 007002 | C192: 授信主体种类 | D192: Credit type | E192: 单一法人授信，集团客户授信，供应链融资，个人客户授信，同业客户授信，其他-银行自定义。无法以枚举类型填报的，以“其他-XX”填报，其中XX为银行自定义种类。 | F192: C..60
B193: 007003 | C193: 授信种类 | D193: Credit granting type | E193: 综合额度授信，低风险额度授信，信用卡额度授信，临时额度授信，专项额度授信，其他-银行自定义。无法以枚举类型填报的，以“其他-XX”填报，其中XX为银行自定义种类。 | F193: C..60
B194: 007004 | C194: 信用卡授信类型 | D194: Credit card granting type | E194: 新发卡授信、固定额度上调,临时额度上调,专项分期额度上调,其他-银行自定义。无法以枚举类型填报的，以“其他-XX”填报，其中XX为银行自定义类型。 | F194: C..60
B195: 007005 | C195: 有效状态 | D195: Validity status | E195: 有效，无效。 | F195: C6
B196: 007006 | C196: 审批意见 | D196: Decision | E196: 银行自定义。 | F196: C..1000
B197: 007007 | C197: 贷款展期编号 | D197: Number of loan extension | E197: 贷款展期编号。 | F197: C..60
B198: 007008 | C198: 信贷资产类型 | D198: Loan asset type | E198: 个人贷款，对公贷款，信用卡贷款。 | F198: C..20
B199: 007009 | C199: 变动方式 | D199: Variation way | E199: 人工，自动。 | F199: C..30
B200: 007010 | C200: 协议名称 | D200: Agreement name | E200: 银行自定义。 | F200: C..400
B201: 007011 | C201: 变动原因 | D201: Happen reason | E201: 中文字典或中文描述，银行自定义。 | F201: C..30
B202: 007012 | C202: 转让方式 | D202: Transfer method | E202: 直接转让，信贷资产证券化，信贷资产收益权转让，信贷资产受益权转让，其他-银行自定义。无法以枚举类型填报的，以“其他-XX”填报，其中“XX”为银行自定义方式。 | F202: C..60
... B206: 007016 | C206: 转让交易平台 | D206: Trading asset Registry | E206: 银登中心，证券交易所，银行间市场，其他-银行自定义。无法以枚举类型填报的，以“其他-XX”填报，其中“XX”为银行自定义交易平台。 | F206: C..20
A207: 资产负债及涉农统计 | B207: 008
B208: 008001 | C208: 期限类型 | D208: Term type | E208: 天，周，旬，月，季，半年，年。 | F208: C..6
A209: 客户风险统计相关指标 | B209: 009
B210: 009001 | C210: 账户类型 | D210: Account type | E210: 银行账户，交易账户。 | F210: C12
...

Sheet 数据结构
A2: 中国银保监会银行业金融机构监管数据标准化规范（2021版）
A4: 分类 | B4: 分类编号 | C4: 传输文件名称 | D4: 表名 | E4: 表编号 | F4: 数据项名称 | G4: 数据项代码 | H4: 数据项编号 | I4: 数据元 | J4: 数据元编码 | K4: 数据元说明 | L4: 格式 | M4: 备注 | N4: 变更类型 | O4: 变更规范列 | P4: 变更说明
A6: 公共信息 | B6: 001
C7: JGXXB | D7: 机构信息表 | E7: 101 | M7: =INDEX(表结构总览!E:H,MATCH(D7,表结构总览!E:E,0),4) -> 本表报送银行机构或业务中心信息，业务中心包含管理机构、营业机构、内设机构、虚拟机构。对于营业机构、内设机构、虚拟机构，银行机构代码、金融许可证号等字段可以取上级机构或者本级实体机构对应的信息。境外机构也需要报送，根据实际情况无法填报的字段可以为空。子公司不必报送。机构永久关停、撤销等情况的，在报送最后状态的次月可不再报送。 | N7: 修改 | O7: 备注
F8: 银行机构代码 | G8: YHJGDM | H8: 10101 | I8: 银行机构代码 | J8: =INDEX(数据元说明!A:F,MATCH(I8,数据元说明!C:C,0),2) -> 001010 | K8: =INDEX(数据元说明!A:F,MATCH(I8,数据元说明!C:C,0),5) -> 12位人行支付行号或SWIFT行号。 | L8: =INDEX(数据元说明!A:F,MATCH(I8,数据元说明!C:C,0),6) -> C..30 | M8: 需填报人行大小额支付系统中登记的“人行支付行号”；允许多个内部机构号对应同一个“人行支付行号”；该字段不可为空，内设机构、虚拟机构等无“人行支付行号”的，填报上一级机构的“人行支付行号”。
F9: 内部机构号 | G9: NBJGH | H9: 10102 | I9: 内部机构号 | J9: =INDEX(数据元说明!A:F,MATCH(I9,数据元说明!C:C,0),2) -> 001012 | K9: =INDEX(数据元说明!A:F,MATCH(I9,数据元说明!C:C,0),5) -> 银行内部机构号。应具有标识机构的唯一性。 | L9: =INDEX(数据元说明!A:F,MATCH(I9,数据元说明!C:C,0),6) -> C..30 | M9: PK
F10: 金融许可证号 | G10: JRXKZH | H10: 10103 | I10: 金融许可证号 | J10: =INDEX(数据元说明!A:F,MATCH(I10,数据元说明!C:C,0),2) -> 001011 | K10: =INDEX(数据元说明!A:F,MATCH(I10,数据元说明!C:C,0),5) -> 金融许可证机构编码编制规则（试行） 一、机构编码结构 机构编码由大写英文字母和数字组成，共15位。分六个部分，分别是机构类型代码、机构代码、组织类别代码、发证机关代码、地址代码、顺序代码，从左至右顺序排列，如下表所示。 二、机构编码含义 （一）第［一］位是机构类型代码，用大写英文字母表示。 A-政策性银行 B-商业银行 C-农村合作银行 D-城市信用社 E-农村信用社 F-资金互助社 J-金融资产管理公司 K-信托公司 L-财务公司 M-金融租赁公司 N-汽车金融公司 P-货币经纪公司 Q-贷款公司 Z-其他类金融机构 新增机构类型时，根据需要确定机构类型代码。 （二）第［二］位至第［五］位是机构代码，用数字表示。 1.每个法人机构指定唯一的代码，由计算机系统按照规则自动生成。除农村信用社、资金互助社、贷款公司（E、F、Q类机构）外，全国统一编码。E、F、Q类机构在省（自治区、直辖市）范围内统一编码。 2.新设立的机构依照所属机构类型顺序排列。 机构代码编码示例如下： A-政策性银行 0001-国家开发银行 …… B-商业银行 0001-中国工商银行股份有限公司 …… C-农村合作银行 0001-天津大港农村合作银行 …… D-城市信用社 0001-邯郸市城市信用社股份有限公司 …… E-农村信用社天津市 0001-天津市宝坻区农村信用合作联社 …… 新疆维吾尔自治区 0001-新疆维吾尔自治区农村信用社联合社 …… F-资金互助社 吉林省 0001-吉林省梨树县闰家村百信农村资金互助社 …… 青海省 0001-青海省乐都县雨润镇兴乐农村资金互助社 …… J-金融资产管理公司 0001-中国华融资产管理公司 …… K-信托投资公司 0001-中诚信托投资有限责任公司 …… L-财务公司 0001-中海石油财务有限责任公司 …… M-金融租赁公司 0001-中国外贸金融租赁公司 …… N-汽车金融公司 0001-大众汽车金融（中国）有限公司 …… P-货币经纪公司 0001-上海国利货币经纪有限公司 …… Q-贷款公司四川省 0001-四川省仪陇县惠民贷款有限责任公司 …… 新疆维吾尔自治区 0001- …… Z-其他类金融机构 0001-中央国债登记结算有限责任公司 …… （三）第〔六〕位是组织类别代码，用大写英文字母表示。 机构类型不同，组织类别代码的含义不同。定义如下： 1.A-政策性银行 H-总行 G-总行营业部 H-级分行 K-一级分行营业部 M-二级分行 S-支行 X-其他分支机构 2.B-商业银行 H-总行 G-总行营业部、专营机构 B-一级分行 K-一级分行营业部 L-二级分行 M-直属支行 N-二级分行营业部 S-支行 U-分理处、办事处、营业所 V-储蓄所 X-其他分支机构 3.C-农村合作银行 H-总行 S-支行 U-分理处 V-储蓄所 X-其他分支机构 4.D-城市信用社 H-法人 S-分社、营业部 X-其他分支机构 5.E-农村信用社 H-省（自治区、直辖市）联合社 B-地（市）联合社、联社 S-县（市）联合社、联社、合作社（县级） T-信用合作社 U-信用社、分社 V-储蓄所 X-其他分支机构 6.F-资金互助社 H-法人 7.J-金融资产管理公司 H-总公司 B-办事处 X-其他分支机构 8.K-信托公司 H-法人 9.N-汽车金融公司 H-法人 10.L-财务公司 H-总公司 B-分公司 X-其他分支机构 11.M-金融租赁公司 H-总公司 B-分公司 X-其他分支机构 12.P-货币经纪公司 H-总公司 B-分公司 X-其他分支机构 13.Q-贷款公司 H-总公司 B-分公司 X-其他分支机构 14.Z-其他类金融机构 Z类机构组织类别代码编码方法参照以上规则。 新增机构类型时，参照以上规则，根据实际情况定义其组织类别代码。 （四）第〔七〕位是发证机关代码，用数字表示。 1-银保监会 2-银监局 3-银监分局 （五）第〔八〕位至第〔十一〕是地址代码，用数字表示。按照《中华人民共和国行政区划代码》 （GB/T2260），取市（地区、自治州、盟）、直辖市行政区划代码前四位，作为地址代码。 地址代码示例如下：1100表示北京市，1200表示天津市，1301表示石家庄市，…… （六）第〔十二〕位至第〔十五〕位是顺序代码，用数字表示。机构类型代码、机构代码、组织类别代码、发证机关代码和地址代码相同的机构按照制发金融许可证的顺序编码。 三、机构编码的编制规则 编制机构编码时，按照从左至右的顺序依次确定机构类型代码、机构代码、组织类别代码、发证机关代码、地址代码、顺序代码，由计算机自动生成。 为了保证机构编码的唯一性，以利于电子计算机较长时间地存储数据，因行政许可变更需换发金融许可证，涉及机构编码变更的，原机构编码不再使用.金融机构终止的，机构编码不再使用。注销开业许可收回金融许可证的，机构编码不再使用。 | L10: =INDEX(数据元说明!A:F,MATCH(I10,数据元说明!C:C,0),6) -> C..30 | M10: 营业机构、管理机构必须填报“金融许可证号”，内设机构、虚拟机构及营业部取上一级管理机构的金融许可证号。 | N10: 修改 | O10: 备注
F11: 营业执照号 | G11: YYZZH | H11: 10104 | I11: 营业执照号 | J11: =INDEX(数据元说明!A:F,MATCH(I11,数据元说明!C:C,0),2) -> 002014 | K11: =INDEX(数据元说明!A:F,MATCH(I11,数据元说明!C:C,0),5) -> 已登记统一社会信用代码的，填18位统一社会信用代码；未登记统一社会信用代码的，按原有方式填写。 | L11: =INDEX(数据元说明!A:F,MATCH(I11,数据元说明!C:C,0),6) -> C..60 | M11: 营业机构、管理机构必须填报“营业执照号”，内设机构、虚拟机构及营业部取上一级管理机构的营业执照号 | N11: 修改 | O11: 备注
F12: 银行机构名称 | G12: YHJGMC | H12: 10105 | I12: 名称 | J12: =INDEX(数据元说明!A:F,MATCH(I12,数据元说明!C:C,0),2) -> 001001 | K12: =INDEX(数据元说明!A:F,MATCH(I12,数据元说明!C:C,0),5) -> 名称应与公章所使用的名称完全一致。银行机构以银保监会金融机构许可证登记名称为准。无独立金融机构许可证的机构，可在本名称中体现出机构特征。第三方支付平台填报第三方支付平台名称。 客户名称按照客户的不同类型按如下标准填报。 （1）集团客户，填报银行对该集团授信采用的集团客户名称。视同集团客户填报的供应链融资填报核心企业客户名称。 （2）单一法人客户，经有关部门批准正式使用的全称，与公章所使用的名称完全一致。视同单一法人客户填报的分公司，填报分公司全称，与分公司公章所使用的名称完全一致。客户是境内涉密机构的，客户名称填报为“*********”。 （3）同业客户，经有关部门批准正式使用的客户全称，与客户公章所使用的名称完全一致。 （4）自然人，与有效证件上的姓名一致。 （5）境外客户，客户名称应尽量以中文翻译填报，如没有可填报英文名称。 | L12: =INDEX(数据元说明!A:F,MATCH(I12,数据元说明!C:C,0),6) -> C..400 | M12: 需填写全称，有金融许可证号的需与金融许可证上的机构名称保持一致。例如：应填报“XX银行股份有限公司XX省分行”，不应填报为“XX省分行”。无独立金融机构许可证的机构，可在本名称中体现出机构特征。 | N12: 修改 | O12: 格式
F13: 机构类别 | G13: JGLB | H13: 10106 | I13: 机构类别 | J13: =INDEX(数据元说明!A:F,MATCH(I13,数据元说明!C:C,0),2) -> 001013 | K13: =INDEX(数据元说明!A:F,MATCH(I13,数据元说明!C:C,0),5) -> 管理机构，营业机构，虚拟机构，内设机构。 | L13: =INDEX(数据元说明!A:F,MATCH(I13,数据元说明!C:C,0),6) -> C..30 | M13: 仅允许填报为：管理机构，营业机构，虚拟机构，内设机构。 各行根据实际情况进行映射： 管理机构：总行、一级分行、专营机构； 营业机构：除总行、一级分行、专营机构以外的有金融许可证的实体机构。专营机构分支机构作为营业机构。营业部也作为营业机构，填报上一级管理机构的金融许可证号； 虚拟机构：指自助银行、ATM、网银、手机银行等渠道； 内设机构：如清算中心等内设部门。 | N13: 修改 | O13: 数据元说明、备注
F14: 行政区划代码 | G14: XZQHDM | H14: 10107 | I14: 地区代码 | J14: =INDEX(数据元说明!A:F,MATCH(I14,数据元说明!C:C,0),2) -> 001031 | K14: =INDEX(数据元说明!A:F,MATCH(I14,数据元说明!C:C,0),5) -> 境内地区参照《GB/T 2260-2020 中华人民共和国行政区划代码》填写国内行政区划代码，填写至二级分类，如110100。境外地区参照《GB/T 2659 世界各国和地区名称代码》定义的三字符代码，如USA。 | L14: =INDEX(数据元说明!A:F,MATCH(I14,数据元说明!C:C,0),6) -> C..6 | M14: 营业机构、管理机构必须填报实际的“行政区划代码”（要求到区县一级，6位代码），内设机构、虚拟机构，营业部取上一级管理机构的行政区划代码 | N14: 新增
F15: 营业状态 | G15: YYZT | H15: 10108 | I15: 营业状态 | J15: =INDEX(数据元说明!A:F,MATCH(I15,数据元说明!C:C,0),2) -> 001015 | K15: =INDEX(数据元说明!A:F,MATCH(I15,数据元说明!C:C,0),5) -> 营业，停业。 | L15: =INDEX(数据元说明!A:F,MATCH(I15,数据元说明!C:C,0),6) -> C6 | M15: 营业：正常、拟撤销等状态的机构 停业：歇业、筹建中等状态的机构
F16: 成立日期 | G16: CLRQ | H16: 10109 | I16: 日期 | J16: =INDEX(数据元说明!A:F,MATCH(I16,数据元说明!C:C,0),2) -> 001005 | K16: =INDEX(数据元说明!A:F,MATCH(I16,数据元说明!C:C,0),5) -> YYYYMMDD，默认值99991231。 | L16: =INDEX(数据元说明!A:F,MATCH(I16,数据元说明!C:C,0),6) -> C8 | N16: 修改 | O16: 数据项名称、数据项代码
F17: 机构地址 | G17: JGDZ | H17: 10110 | I17: 地址 | J17: =INDEX(数据元说明!A:F,MATCH(I17,数据元说明!C:C,0),2) -> 001008 | K17: =INDEX(数据元说明!A:F,MATCH(I17,数据元说明!C:C,0),5) -> 中文描述。个人填报个人住址。机构填报有关部门批准的有效证件上登记的地址。参照《企业法人营业执照》中的注册地填报，要写明省（区、市）、地（区、市、州、盟）、县（区、市、旗）。境外机构及境内涉密机构不填报。 | L17: =INDEX(数据元说明!A:F,MATCH(I17,数据元说明!C:C,0),6) -> C..400 | M17: 虚拟机构可为空
F18: 机构联系电话 | G18: JGLXDH | H18: 10111 | I18: 电话 | J18: =INDEX(数据元说明!A:F,MATCH(I18,数据元说明!C:C,0),2) -> 001009 | K18: =INDEX(数据元说明!A:F,MATCH(I18,数据元说明!C:C,0),5) -> 手机号码或者区号-固定电话号码。 | L18: =INDEX(数据元说明!A:F,MATCH(I18,数据元说明!C:C,0),6) -> C..30 | M18: 机构办公联系电话，区号-座机电话，虚拟机构、自助银行及自助设备机构、机构本部和仅承担内部核算职能的机构可为空。非隐私，不做变形。 | N18: 新增
F19: 负责人姓名 | G19: FZRXM | H19: 10112 | I19: 姓名 | J19: =INDEX(数据元说明!A:F,MATCH(I19,数据元说明!C:C,0),2) -> 001017 | K19: =INDEX(数据元说明!A:F,MATCH(I19,数据元说明!C:C,0),5) -> 姓名。 | L19: =INDEX(数据元说明!A:F,MATCH(I19,数据元说明!C:C,0),6) -> C..200 | M19: 非隐私，不做变形。虚拟机构、自助银行及自助设备机构、机构本部和仅承担内部核算职能的机构可为空。
F20: 负责人职务 | G20: FZRZW | H20: 10113 | I20: 职务 | J20: =INDEX(数据元说明!A:F,MATCH(I20,数据元说明!C:C,0),2) -> 001019 | K20: =INDEX(数据元说明!A:F,MATCH(I20,数据元说明!C:C,0),5) -> 中文字典或中文描述，银行自定义。 | L20: =INDEX(数据元说明!A:F,MATCH(I20,数据元说明!C:C,0),6) -> C..200 | M20: 虚拟机构、自助银行及自助设备机构、机构本部和仅承担内部核算职能的机构可为空。
F21: 负责人联系电话 | G21: FZRLXDH | H21: 10114 | I21: 电话 | J21: =INDEX(数据元说明!A:F,MATCH(I21,数据元说明!C:C,0),2) -> 001009 | K21: =INDEX(数据元说明!A:F,MATCH(I21,数据元说明!C:C,0),5) -> 手机号码或者区号-固定电话号码。 | L21: =INDEX(数据元说明!A:F,MATCH(I21,数据元说明!C:C,0),6) -> C..30 | M21: 负责人联系电话，区号-座机电话/手机，虚拟机构、自助银行及自助设备机构、机构本部和仅承担内部核算职能的机构可为空。非隐私，不做变形 | N21: 修改 | O21: 备注
F22: 备注 | G22: BBZ | H22: 10115 | I22: 备注 | J22: =INDEX(数据元说明!A:F,MATCH(I22,数据元说明!C:C,0),2) -> 001040 | K22: =INDEX(数据元说明!A:F,MATCH(I22,数据元说明!C:C,0),5) -> 银行自定义。 | L22: =INDEX(数据元说明!A:F,MATCH(I22,数据元说明!C:C,0),6) -> C..600 | M22: 描述其他字段未能详尽说明的情况，如是否是历史数据、未通过校验原因等可在备注栏说明，简述即可，不必详述，不同备注事项用分号或句号分隔开。 | N22: 新增
F23: 采集日期 | G23: CJRQ | H23: 10116 | I23: 日期 | J23: =INDEX(数据元说明!A:F,MATCH(I23,数据元说明!C:C,0),2) -> 001005 | K23: =INDEX(数据元说明!A:F,MATCH(I23,数据元说明!C:C,0),5) -> YYYYMMDD，默认值99991231。 | L23: =INDEX(数据元说明!A:F,MATCH(I23,数据元说明!C:C,0),6) -> C8 | M23: PK。采集日期指该期（批次）数据报送的期末日期，例如：按日采集的表，采集日期应为每日；按月采集的表，采集日期应为月末最后一天；以此类推。有特殊报送要求的，应以报送要求的截至日期为采集日期。
C24: YGB | D24: 员工表 | E24: 102 | M24: =INDEX(表结构总览!E:H,MATCH(D24,表结构总览!E:E,0),4) -> 在职类正式/非正式员工需每月报送，非正式员工包括合同制、劳务派遣员工。员工状态转为离职、退休、开除、死亡、调出等的，在报送该员工最后状态的次月可不再报送。子公司员工不用报送，调动至子公司的员工按离职报送。董事、监事不用报送。 | N24: 修改 | O24: 备注
F25: 银行机构代码 | G25: YHJGDM | H25: 10201 | I25: 银行机构代码 | J25: =INDEX(数据元说明!A:F,MATCH(I25,数据元说明!C:C,0),2) -> 001010 | K25: =INDEX(数据元说明!A:F,MATCH(I25,数据元说明!C:C,0),5) -> 12位人行支付行号或SWIFT行号。 | L25: =INDEX(数据元说明!A:F,MATCH(I25,数据元说明!C:C,0),6) -> C..30 | M25: 关联数据项：机构信息表.银行机构代码
F26: 金融许可证号 | G26: JRXKZH | H26: 10202 | I26: 金融许可证号 | J26: =INDEX(数据元说明!A:F,MATCH(I26,数据元说明!C:C,0),2) -> 001011 | K26: =INDEX(数据元说明!A:F,MATCH(I26,数据元说明!C:C,0),5) -> 金融许可证机构编码编制规则（试行） 一、机构编码结构 机构编码由大写英文字母和数字组成，共15位。分六个部分，分别是机构类型代码、机构代码、组织类别代码、发证机关代码、地址代码、顺序代码，从左至右顺序排列，如下表所示。 二、机构编码含义 （一）第［一］位是机构类型代码，用大写英文字母表示。 A-政策性银行 B-商业银行 C-农村合作银行 D-城市信用社 E-农村信用社 F-资金互助社 J-金融资产管理公司 K-信托公司 L-财务公司 M-金融租赁公司 N-汽车金融公司 P-货币经纪公司 Q-贷款公司 Z-其他类金融机构 新增机构类型时，根据需要确定机构类型代码。 （二）第［二］位至第［五］位是机构代码，用数字表示。 1.每个法人机构指定唯一的代码，由计算机系统按照规则自动生成。除农村信用社、资金互助社、贷款公司（E、F、Q类机构）外，全国统一编码。E、F、Q类机构在省（自治区、直辖市）范围内统一编码。 2.新设立的机构依照所属机构类型顺序排列。 机构代码编码示例如下： A-政策性银行 0001-国家开发银行 …… B-商业银行 0001-中国工商银行股份有限公司 …… C-农村合作银行 0001-天津大港农村合作银行 …… D-城市信用社 0001-邯郸市城市信用社股份有限公司 …… E-农村信用社天津市 0001-天津市宝坻区农村信用合作联社 …… 新疆维吾尔自治区 0001-新疆维吾尔自治区农村信用社联合社 …… F-资金互助社 吉林省 0001-吉林省梨树县闰家村百信农村资金互助社 …… 青海省 0001-青海省乐都县雨润镇兴乐农村资金互助社 …… J-金融资产管理公司 0001-中国华融资产管理公司 …… K-信托投资公司 0001-中诚信托投资有限责任公司 …… L-财务公司 0001-中海石油财务有限责任公司 …… M-金融租赁公司 0001-中国外贸金融租赁公司 …… N-汽车金融公司 0001-大众汽车金融（中国）有限公司 …… P-货币经纪公司 0001-上海国利货币经纪有限公司 …… Q-贷款公司四川省 0001-四川省仪陇县惠民贷款有限责任公司 …… 新疆维吾尔自治区 0001- …… Z-其他类金融机构 0001-中央国债登记结算有限责任公司 …… （三）第〔六〕位是组织类别代码，用大写英文字母表示。 机构类型不同，组织类别代码的含义不同。定义如下： 1.A-政策性银行 H-总行 G-总行营业部 H-级分行 K-一级分行营业部 M-二级分行 S-支行 X-其他分支机构 2.B-商业银行 H-总行 G-总行营业部、专营机构 B-一级分行 K-一级分行营业部 L-二级分行 M-直属支行 N-二级分行营业部 S-支行 U-分理处、办事处、营业所 V-储蓄所 X-其他分支机构 3.C-农村合作银行 H-总行 S-支行 U-分理处 V-储蓄所 X-其他分支机构 4.D-城市信用社 H-法人 S-分社、营业部 X-其他分支机构 5.E-农村信用社 H-省（自治区、直辖市）联合社 B-地（市）联合社、联社 S-县（市）联合社、联社、合作社（县级） T-信用合作社 U-信用社、分社 V-储蓄所 X-其他分支机构 6.F-资金互助社 H-法人 7.J-金融资产管理公司 H-总公司 B-办事处 X-其他分支机构 8.K-信托公司 H-法人 9.N-汽车金融公司 H-法人 10.L-财务公司 H-总公司 B-分公司 X-其他分支机构 11.M-金融租赁公司 H-总公司 B-分公司 X-其他分支机构 12.P-货币经纪公司 H-总公司 B-分公司 X-其他分支机构 13.Q-贷款公司 H-总公司 B-分公司 X-其他分支机构 14.Z-其他类金融机构 Z类机构组织类别代码编码方法参照以上规则。 新增机构类型时，参照以上规则，根据实际情况定义其组织类别代码。 （四）第〔七〕位是发证机关代码，用数字表示。 1-银保监会 2-银监局 3-银监分局 （五）第〔八〕位至第〔十一〕是地址代码，用数字表示。按照《中华人民共和国行政区划代码》 （GB/T2260），取市（地区、自治州、盟）、直辖市行政区划代码前四位，作为地址代码。 地址代码示例如下：1100表示北京市，1200表示天津市，1301表示石家庄市，…… （六）第〔十二〕位至第〔十五〕位是顺序代码，用数字表示。机构类型代码、机构代码、组织类别代码、发证机关代码和地址代码相同的机构按照制发金融许可证的顺序编码。 三、机构编码的编制规则 编制机构编码时，按照从左至右的顺序依次确定机构类型代码、机构代码、组织类别代码、发证机关代码、地址代码、顺序代码，由计算机自动生成。 为了保证机构编码的唯一性，以利于电子计算机较长时间地存储数据，因行政许可变更需换发金融许可证，涉及机构编码变更的，原机构编码不再使用.金融机构终止的，机构编码不再使用。注销开业许可收回金融许可证的，机构编码不再使用。 | L26: =INDEX(数据元说明!A:F,MATCH(I26,数据元说明!C:C,0),6) -> C..30 | M26: 营业机构、管理机构必须填报“金融许可证号”，内设机构、虚拟机构及营业部取上一级管理机构的金融许可证号。 | N26: 修改 | O26: 备注
F27: 内部机构号 | G27: NBJGH | H27: 10203 | I27: 内部机构号 | J27: =INDEX(数据元说明!A:F,MATCH(I27,数据元说明!C:C,0),2) -> 001012 | K27: =INDEX(数据元说明!A:F,MATCH(I27,数据元说明!C:C,0),5) -> 银行内部机构号。应具有标识机构的唯一性。 | L27: =INDEX(数据元说明!A:F,MATCH(I27,数据元说明!C:C,0),6) -> C..30 | M27: 关联数据项：机构信息表.内部机构号。员工如果采集区间发生过更换机构，按采集时点的最后填报内部机构号。 | N27: 修改 | O27: 备注
F28: 银行机构名称 | G28: YHJGMC | H28: 10204 | I28: 名称 | J28: =INDEX(数据元说明!A:F,MATCH(I28,数据元说明!C:C,0),2) -> 001001 | K28: =INDEX(数据元说明!A:F,MATCH(I28,数据元说明!C:C,0),5) -> 名称应与公章所使用的名称完全一致。银行机构以银保监会金融机构许可证登记名称为准。无独立金融机构许可证的机构，可在本名称中体现出机构特征。第三方支付平台填报第三方支付平台名称。 客户名称按照客户的不同类型按如下标准填报。 （1）集团客户，填报银行对该集团授信采用的集团客户名称。视同集团客户填报的供应链融资填报核心企业客户名称。 （2）单一法人客户，经有关部门批准正式使用的全称，与公章所使用的名称完全一致。视同单一法人客户填报的分公司，填报分公司全称，与分公司公章所使用的名称完全一致。客户是境内涉密机构的，客户名称填报为“*********”。 （3）同业客户，经有关部门批准正式使用的客户全称，与客户公章所使用的名称完全一致。 （4）自然人，与有效证件上的姓名一致。 （5）境外客户，客户名称应尽量以中文翻译填报，如没有可填报英文名称。 | L28: =INDEX(数据元说明!A:F,MATCH(I28,数据元说明!C:C,0),6) -> C..400 | M28: 需填写全称，有金融许可证号的需与金融许可证上的机构名称保持一致。关联数据项：机构信息表.银行机构名称 | N28: 修改 | O28: 格式
F29: 工号 | G29: GH | H29: 10205 | I29: 工号 | J29: =INDEX(数据元说明!A:F,MATCH(I29,数据元说明!C:C,0),2) -> 001016 | K29: =INDEX(数据元说明!A:F,MATCH(I29,数据元说明!C:C,0),5) -> 工号，银行自定义。 | L29: =INDEX(数据元说明!A:F,MATCH(I29,数据元说明!C:C,0),6) -> C..30 | M29: PK。 | N29: 修改 | P29: 调整数据项位置
F30: 姓名 | G30: XM | H30: 10206 | I30: 姓名 | J30: =INDEX(数据元说明!A:F,MATCH(I30,数据元说明!C:C,0),2) -> 001017 | K30: =INDEX(数据元说明!A:F,MATCH(I30,数据元说明!C:C,0),5) -> 姓名。 | L30: =INDEX(数据元说明!A:F,MATCH(I30,数据元说明!C:C,0),6) -> C..200 | M30: 员工姓名为非隐私，不做变形。 | N30: 修改 | O30: 备注
F31: 证件类别 | G31: ZJLB | H31: 10207 | I31: 证件类别 | J31: =INDEX(数据元说明!A:F,MATCH(I31,数据元说明!C:C,0),2) -> 002002 | K31: =INDEX(数据元说明!A:F,MATCH(I31,数据元说明!C:C,0),5) -> 同业客户：银行机构代码，金融许可证号，SWIFT编码，其他-XX。 对公客户：统一社会信用代码，组织机构代码，营业执照（工商注册号），公司注册证书，全球法人识别码，其他-XX。 个人客户：居民身份证，军官证，文职干部证，警官证，士兵证，户口簿，临时身份证，其他有效通行旅行证件，护照，学生证，无证件，其他-XX。 无法以枚举类型填报的，以“其他-XX”报送，其中“XX”为银行自定义类型。 对公客户优先填报统一社会信用代码，没有统一社会信用代码的对公客户填报组织机构代码。组织机构代码、统一社会信用代码均没有的可以填报客户提供的批文文号、开户主证件、上级机构统一社会信用代码等，以“其他-XX”填报。 | L31: =INDEX(数据元说明!A:F,MATCH(I31,数据元说明!C:C,0),6) -> C..60
F32: 证件号码 | G32: ZJHM | H32: 10208 | I32: 证件号码 | J32: =INDEX(数据元说明!A:F,MATCH(I32,数据元说明!C:C,0),2) -> 002003 | K32: =INDEX(数据元说明!A:F,MATCH(I32,数据元说明!C:C,0),5) -> 与证件类别对应的证件号码。涉及个人身份证件时需按照本规范给定规则进行脱敏处理。 | L32: =INDEX(数据元说明!A:F,MATCH(I32,数据元说明!C:C,0),6) -> C..70 | M32: 隐私，银行机构变形。变形规则见《采集技术接口说明》。 | N32: 修改 | O32: 数据项代码 | P32: 调整数据项位置
F33: 联系电话 | G33: LXDH | H33: 10209 | I33: 电话 | J33: =INDEX(数据元说明!A:F,MATCH(I33,数据元说明!C:C,0),2) -> 001009 | K33: =INDEX(数据元说明!A:F,MATCH(I33,数据元说明!C:C,0),5) -> 手机号码或者区号-固定电话号码。 | L33: =INDEX(数据元说明!A:F,MATCH(I33,数据元说明!C:C,0),6) -> C..30 | M33: 非隐私，不做变形。 | N33: 修改 | O33: 备注
F34: 所属部门 | G34: SSBM | H34: 10210 | I34: 所属部门 | J34: =INDEX(数据元说明!A:F,MATCH(I34,数据元说明!C:C,0),2) -> 001018 | K34: =INDEX(数据元说明!A:F,MATCH(I34,数据元说明!C:C,0),5) -> 中文字典或中文描述，银行自定义。 | L34: =INDEX(数据元说明!A:F,MATCH(I34,数据元说明!C:C,0),6) -> C..200
F35: 岗位编号 | G35: GWBH | H35: 10211 | I35: 岗位编号 | J35: =INDEX(数据元说明!A:F,MATCH(I35,数据元说明!C:C,0),2) -> 001025 | K35: =INDEX(数据元说明!A:F,MATCH(I35,数据元说明!C:C,0),5) -> 银行自定义。 | L35: =INDEX(数据元说明!A:F,MATCH(I35,数据元说明!C:C,0),6) -> C..60 | M35: PK。存在多个岗位时，按照多条报送。关联数据项：岗位信息表.岗位编号。 | N35: 修改 | O35: 备注 | P35: 增加备注说明
F36: 岗位名称 | G36: GWMC | H36: 10212 | I36: 岗位名称 | J36: =INDEX(数据元说明!A:F,MATCH(I36,数据元说明!C:C,0),2) -> 001027 | K36: =INDEX(数据元说明!A:F,MATCH(I36,数据元说明!C:C,0),5) -> 岗位名称，中文字典或中文描述，银行自定义。 | L36: =INDEX(数据元说明!A:F,MATCH(I36,数据元说明!C:C,0),6) -> C..200 | M36: 存在多个岗位时，按照多条报送。关联数据项：岗位信息表.岗位名称 | N36: 新增
F37: 员工状态 | G37: YGZT | H37: 10213 | I37: 员工状态 | J37: =INDEX(数据元说明!A:F,MATCH(I37,数据元说明!C:C,0),2) -> 001037 | K37: =INDEX(数据元说明!A:F,MATCH(I37,数据元说明!C:C,0),5) -> 正式员工离职，正式员工在职，非正式员工离职，非正式员工在职，内退，退休，开除，死亡，调出，其他-银行自定义。无法以枚举类型填报的，以“其他-XX”填报，其中“XX”为银行自定义类型。 | L37: =INDEX(数据元说明!A:F,MATCH(I37,数据元说明!C:C,0),6) -> C..30 | M37: 正式员工停职属于正式员工在职,借调、挂职、病休等均属于正式员工在职类,非正式员工停职属于非正式员工在职,开除包括劝退、辞退等员工非主动离职，调出指本行系统内调动，如从北京分行调至总行。 | N37: 修改 | O37: 数据元、备注 | P37: 增加备注说明
F38: 备注 | G38: BBZ | H38: 10214 | I38: 备注 | J38: =INDEX(数据元说明!A:F,MATCH(I38,数据元说明!C:C,0),2) -> 001040 | K38: =INDEX(数据元说明!A:F,MATCH(I38,数据元说明!C:C,0),5) -> 银行自定义。 | L38: =INDEX(数据元说明!A:F,MATCH(I38,数据元说明!C:C,0),6) -> C..600 | M38: 描述其他字段未能详尽说明的情况，如是否是历史数据、未通过校验原因等可在备注栏说明，简述即可，不必详述，不同备注事项用分号或句号分隔开。 | N38: 新增
F39: 采集日期 | G39: CJRQ | H39: 10215 | I39: 日期 | J39: =INDEX(数据元说明!A:F,MATCH(I39,数据元说明!C:C,0),2) -> 001005 | K39: =INDEX(数据元说明!A:F,MATCH(I39,数据元说明!C:C,0),5) -> YYYYMMDD，默认值99991231。 | L39: =INDEX(数据元说明!A:F,MATCH(I39,数据元说明!C:C,0),6) -> C8 | M39: PK。采集日期指该期（批次）数据报送的期末日期，例如：按日采集的表，采集日期应为每日；按月采集的表，采集日期应为月末最后一天；以此类推。有特殊报送要求的，应以报送要求的截至日期为采集日期。
C40: GYB | D40: 柜员表 | E40: 103 | M40: =INDEX(表结构总览!E:H,MATCH(D40,表结构总览!E:E,0),4) -> 包含实体柜员和虚拟柜员。为虚拟柜员时，工号、银行机构代码等字段依业务实际填列或留为缺失值，如报送虚拟柜员，则通过“柜员类型”字段进行区分；柜员状态转为注销、无效等时，可在报送该条数据最终状态的次月不再报送。 | N40: 修改 | O40: 备注 | P40: 增加备注说明
F41: 银行机构代码 | G41: YHJGDM | H41: 10301 | I41: 银行机构代码 | J41: =INDEX(数据元说明!A:F,MATCH(I41,数据元说明!C:C,0),2) -> 001010 | K41: =INDEX(数据元说明!A:F,MATCH(I41,数据元说明!C:C,0),5) -> 12位人行支付行号或SWIFT行号。 | L41: =INDEX(数据元说明!A:F,MATCH(I41,数据元说明!C:C,0),6) -> C..30 | M41: 关联数据项：机构信息表.银行机构代码
F42: 金融许可证号 | G42: JRXKZH | H42: 10302 | I42: 金融许可证号 | J42: =INDEX(数据元说明!A:F,MATCH(I42,数据元说明!C:C,0),2) -> 001011 | K42: =INDEX(数据元说明!A:F,MATCH(I42,数据元说明!C:C,0),5) -> 金融许可证机构编码编制规则（试行） 一、机构编码结构 机构编码由大写英文字母和数字组成，共15位。分六个部分，分别是机构类型代码、机构代码、组织类别代码、发证机关代码、地址代码、顺序代码，从左至右顺序排列，如下表所示。 二、机构编码含义 （一）第［一］位是机构类型代码，用大写英文字母表示。 A-政策性银行 B-商业银行 C-农村合作银行 D-城市信用社 E-农村信用社 F-资金互助社 J-金融资产管理公司 K-信托公司 L-财务公司 M-金融租赁公司 N-汽车金融公司 P-货币经纪公司 Q-贷款公司 Z-其他类金融机构 新增机构类型时，根据需要确定机构类型代码。 （二）第［二］位至第［五］位是机构代码，用数字表示。 1.每个法人机构指定唯一的代码，由计算机系统按照规则自动生成。除农村信用社、资金互助社、贷款公司（E、F、Q类机构）外，全国统一编码。E、F、Q类机构在省（自治区、直辖市）范围内统一编码。 2.新设立的机构依照所属机构类型顺序排列。 机构代码编码示例如下： A-政策性银行 0001-国家开发银行 …… B-商业银行 0001-中国工商银行股份有限公司 …… C-农村合作银行 0001-天津大港农村合作银行 …… D-城市信用社 0001-邯郸市城市信用社股份有限公司 …… E-农村信用社天津市 0001-天津市宝坻区农村信用合作联社 …… 新疆维吾尔自治区 0001-新疆维吾尔自治区农村信用社联合社 …… F-资金互助社 吉林省 0001-吉林省梨树县闰家村百信农村资金互助社 …… 青海省 0001-青海省乐都县雨润镇兴乐农村资金互助社 …… J-金融资产管理公司 0001-中国华融资产管理公司 …… K-信托投资公司 0001-中诚信托投资有限责任公司 …… L-财务公司 0001-中海石油财务有限责任公司 …… M-金融租赁公司 0001-中国外贸金融租赁公司 …… N-汽车金融公司 0001-大众汽车金融（中国）有限公司 …… P-货币经纪公司 0001-上海国利货币经纪有限公司 …… Q-贷款公司四川省 0001-四川省仪陇县惠民贷款有限责任公司 …… 新疆维吾尔自治区 0001- …… Z-其他类金融机构 0001-中央国债登记结算有限责任公司 …… （三）第〔六〕位是组织类别代码，用大写英文字母表示。 机构类型不同，组织类别代码的含义不同。定义如下： 1.A-政策性银行 H-总行 G-总行营业部 H-级分行 K-一级分行营业部 M-二级分行 S-支行 X-其他分支机构 2.B-商业银行 H-总行 G-总行营业部、专营机构 B-一级分行 K-一级分行营业部 L-二级分行 M-直属支行 N-二级分行营业部 S-支行 U-分理处、办事处、营业所 V-储蓄所 X-其他分支机构 3.C-农村合作银行 H-总行 S-支行 U-分理处 V-储蓄所 X-其他分支机构 4.D-城市信用社 H-法人 S-分社、营业部 X-其他分支机构 5.E-农村信用社 H-省（自治区、直辖市）联合社 B-地（市）联合社、联社 S-县（市）联合社、联社、合作社（县级） T-信用合作社 U-信用社、分社 V-储蓄所 X-其他分支机构 6.F-资金互助社 H-法人 7.J-金融资产管理公司 H-总公司 B-办事处 X-其他分支机构 8.K-信托公司 H-法人 9.N-汽车金融公司 H-法人 10.L-财务公司 H-总公司 B-分公司 X-其他分支机构 11.M-金融租赁公司 H-总公司 B-分公司 X-其他分支机构 12.P-货币经纪公司 H-总公司 B-分公司 X-其他分支机构 13.Q-贷款公司 H-总公司 B-分公司 X-其他分支机构 14.Z-其他类金融机构 Z类机构组织类别代码编码方法参照以上规则。 新增机构类型时，参照以上规则，根据实际情况定义其组织类别代码。 （四）第〔七〕位是发证机关代码，用数字表示。 1-银保监会 2-银监局 3-银监分局 （五）第〔八〕位至第〔十一〕是地址代码，用数字表示。按照《中华人民共和国行政区划代码》 （GB/T2260），取市（地区、自治州、盟）、直辖市行政区划代码前四位，作为地址代码。 地址代码示例如下：1100表示北京市，1200表示天津市，1301表示石家庄市，…… （六）第〔十二〕位至第〔十五〕位是顺序代码，用数字表示。机构类型代码、机构代码、组织类别代码、发证机关代码和地址代码相同的机构按照制发金融许可证的顺序编码。 三、机构编码的编制规则 编制机构编码时，按照从左至右的顺序依次确定机构类型代码、机构代码、组织类别代码、发证机关代码、地址代码、顺序代码，由计算机自动生成。 为了保证机构编码的唯一性，以利于电子计算机较长时间地存储数据，因行政许可变更需换发金融许可证，涉及机构编码变更的，原机构编码不再使用.金融机构终止的，机构编码不再使用。注销开业许可收回金融许可证的，机构编码不再使用。 | L42: =INDEX(数据元说明!A:F,MATCH(I42,数据元说明!C:C,0),6) -> C..30 | M42: 营业机构、管理机构必须填报“金融许可证号”，内设机构、虚拟机构及营业部取上一级管理机构的金融许可证号。 | N42: 修改 | O42: 备注
F43: 内部机构号 | G43: NBJGH | H43: 10303 | I43: 内部机构号 | J43: =INDEX(数据元说明!A:F,MATCH(I43,数据元说明!C:C,0),2) -> 001012 | K43: =INDEX(数据元说明!A:F,MATCH(I43,数据元说明!C:C,0),5) -> 银行内部机构号。应具有标识机构的唯一性。 | L43: =INDEX(数据元说明!A:F,MATCH(I43,数据元说明!C:C,0),6) -> C..30 | M43: PK。关联数据项：机构信息表.内部机构号
F44: 银行机构名称 | G44: YHJGMC | H44: 10304 | I44: 名称 | J44: =INDEX(数据元说明!A:F,MATCH(I44,数据元说明!C:C,0),2) -> 001001 | K44: =INDEX(数据元说明!A:F,MATCH(I44,数据元说明!C:C,0),5) -> 名称应与公章所使用的名称完全一致。银行机构以银保监会金融机构许可证登记名称为准。无独立金融机构许可证的机构，可在本名称中体现出机构特征。第三方支付平台填报第三方支付平台名称。 客户名称按照客户的不同类型按如下标准填报。 （1）集团客户，填报银行对该集团授信采用的集团客户名称。视同集团客户填报的供应链融资填报核心企业客户名称。 （2）单一法人客户，经有关部门批准正式使用的全称，与公章所使用的名称完全一致。视同单一法人客户填报的分公司，填报分公司全称，与分公司公章所使用的名称完全一致。客户是境内涉密机构的，客户名称填报为“*********”。 （3）同业客户，经有关部门批准正式使用的客户全称，与客户公章所使用的名称完全一致。 （4）自然人，与有效证件上的姓名一致。 （5）境外客户，客户名称应尽量以中文翻译填报，如没有可填报英文名称。 | L44: =INDEX(数据元说明!A:F,MATCH(I44,数据元说明!C:C,0),6) -> C..400 | M44: 需填写全称，有金融许可证号的需与金融许可证上的机构名称保持一致。关联数据项：机构信息表.银行机构名称 | N44: 修改 | O44: 格式
F45: 柜员号 | G45: GYH | H45: 10305 | I45: 柜员号 | J45: =INDEX(数据元说明!A:F,MATCH(I45,数据元说明!C:C,0),2) -> 001021 | K45: =INDEX(数据元说明!A:F,MATCH(I45,数据元说明!C:C,0),5) -> 柜员编号，银行自定义。 | L45: =INDEX(数据元说明!A:F,MATCH(I45,数据元说明!C:C,0),6) -> C..30 | M45: PK，根据实际情况填写，虚拟柜员可填写渠道号。 | N45: 修改 | P45: 调整数据项位置
F46: 工号 | G46: GH | H46: 10306 | I46: 工号 | J46: =INDEX(数据元说明!A:F,MATCH(I46,数据元说明!C:C,0),2) -> 001016 | K46: =INDEX(数据元说明!A:F,MATCH(I46,数据元说明!C:C,0),5) -> 工号，银行自定义。 | L46: =INDEX(数据元说明!A:F,MATCH(I46,数据元说明!C:C,0),6) -> C..30 | M46: 虚拟柜员员工号允许为空。关联数据项：员工表.工号。 | N46: 修改 | P46: 调整数据项位置
F47: 柜员类型 | G47: GYLX | H47: 10307 | I47: 柜员类型 | J47: =INDEX(数据元说明!A:F,MATCH(I47,数据元说明!C:C,0),2) -> 001022 | K47: =INDEX(数据元说明!A:F,MATCH(I47,数据元说明!C:C,0),5) -> 中文字典或中文描述，银行自定义。 | L47: =INDEX(数据元说明!A:F,MATCH(I47,数据元说明!C:C,0),6) -> C..30 | M47: 银行自定义，“柜员类型”需体现具体虚拟柜员，如自助银行，网银等。
F48: 是否实体柜员 | G48: SFSTGY | H48: 10308 | I48: 是否标志 | J48: =INDEX(数据元说明!A:F,MATCH(I48,数据元说明!C:C,0),2) -> 001002 | K48: =INDEX(数据元说明!A:F,MATCH(I48,数据元说明!C:C,0),5) -> 是，否。 | L48: =INDEX(数据元说明!A:F,MATCH(I48,数据元说明!C:C,0),6) -> C3 | M48: 必填，实体柜员填是，其他填否。
F49: 客户经理标志 | G49: KHJLBZ | H49: 10309 | I49: 是否标志 | J49: =INDEX(数据元说明!A:F,MATCH(I49,数据元说明!C:C,0),2) -> 001002 | K49: =INDEX(数据元说明!A:F,MATCH(I49,数据元说明!C:C,0),5) -> 是，否。 | L49: =INDEX(数据元说明!A:F,MATCH(I49,数据元说明!C:C,0),6) -> C3 | M49: 必填。
F50: 信贷员标志 | G50: XDYBZ | H50: 10310 | I50: 是否标志 | J50: =INDEX(数据元说明!A:F,MATCH(I50,数据元说明!C:C,0),2) -> 001002 | K50: =INDEX(数据元说明!A:F,MATCH(I50,数据元说明!C:C,0),5) -> 是，否。 | L50: =INDEX(数据元说明!A:F,MATCH(I50,数据元说明!C:C,0),6) -> C3 | M50: 必填。
F51: 岗位编号 | G51: GWBH | H51: 10311 | I51: 岗位编号 | J51: =INDEX(数据元说明!A:F,MATCH(I51,数据元说明!C:C,0),2) -> 001025 | K51: =INDEX(数据元说明!A:F,MATCH(I51,数据元说明!C:C,0),5) -> 银行自定义。 | L51: =INDEX(数据元说明!A:F,MATCH(I51,数据元说明!C:C,0),6) -> C..60 | M51: 关联数据项：岗位信息表.岗位编号
F52: 柜员权限级别 | G52: GYQXJB | H52: 10312 | I52: 柜员权限级别 | J52: =INDEX(数据元说明!A:F,MATCH(I52,数据元说明!C:C,0),2) -> 001024 | K52: =INDEX(数据元说明!A:F,MATCH(I52,数据元说明!C:C,0),5) -> 柜员权限级别，银行自定义。 | L52: =INDEX(数据元说明!A:F,MATCH(I52,数据元说明!C:C,0),6) -> C..30
F53: 上岗日期 | G53: SGRQ | H53: 10313 | I53: 日期 | J53: =INDEX(数据元说明!A:F,MATCH(I53,数据元说明!C:C,0),2) -> 001005 | K53: =INDEX(数据元说明!A:F,MATCH(I53,数据元说明!C:C,0),5) -> YYYYMMDD，默认值99991231。 | L53: =INDEX(数据元说明!A:F,MATCH(I53,数据元说明!C:C,0),6) -> C8
F54: 柜员状态 | G54: GYZT | H54: 10314 | I54: 员工状态 | J54: =INDEX(数据元说明!A:F,MATCH(I54,数据元说明!C:C,0),2) -> 001037 | K54: =INDEX(数据元说明!A:F,MATCH(I54,数据元说明!C:C,0),5) -> 正式员工离职，正式员工在职，非正式员工离职，非正式员工在职，内退，退休，开除，死亡，调出，其他-银行自定义。无法以枚举类型填报的，以“其他-XX”填报，其中“XX”为银行自定义类型。 | L54: =INDEX(数据元说明!A:F,MATCH(I54,数据元说明!C:C,0),6) -> C..30 | N54: 修改 | O54: 数据元
F55: 备注 | G55: BBZ | H55: 10315 | I55: 备注 | J55: =INDEX(数据元说明!A:F,MATCH(I55,数据元说明!C:C,0),2) -> 001040 | K55: =INDEX(数据元说明!A:F,MATCH(I55,数据元说明!C:C,0),5) -> 银行自定义。 | L55: =INDEX(数据元说明!A:F,MATCH(I55,数据元说明!C:C,0),6) -> C..600 | M55: 描述其他字段未能详尽说明的情况，如是否是历史数据、未通过校验原因等可在备注栏说明，简述即可，不必详述，不同备注事项用分号或句号分隔开。 | N55: 新增
F56: 采集日期 | G56: CJRQ | H56: 10316 | I56: 日期 | J56: =INDEX(数据元说明!A:F,MATCH(I56,数据元说明!C:C,0),2) -> 001005 | K56: =INDEX(数据元说明!A:F,MATCH(I56,数据元说明!C:C,0),5) -> YYYYMMDD，默认值99991231。 | L56: =INDEX(数据元说明!A:F,MATCH(I56,数据元说明!C:C,0),6) -> C8 | M56: PK。采集日期指该期（批次）数据报送的期末日期，例如：按日采集的表，采集日期应为每日；按月采集的表，采集日期应为月末最后一天；以此类推。有特殊报送要求的，应以报送要求的截至日期为采集日期。
C57: GWXXB | D57: 岗位信息表 | E57: 104 | M57: =INDEX(表结构总览!E:H,MATCH(D57,表结构总览!E:E,0),4) -> 银行机构内设立的所有岗位的相关信息，至少应包括核心和人力资源系统中的所有岗位信息。撤销的岗位于次月不再报送。 | N57: 修改
F58: 银行机构代码 | G58: YHJGDM | H58: 10401 | I58: 银行机构代码 | J58: =INDEX(数据元说明!A:F,MATCH(I58,数据元说明!C:C,0),2) -> 001010 | K58: =INDEX(数据元说明!A:F,MATCH(I58,数据元说明!C:C,0),5) -> 12位人行支付行号或SWIFT行号。 | L58: =INDEX(数据元说明!A:F,MATCH(I58,数据元说明!C:C,0),6) -> C..30 | M58: 关联数据项：机构信息表.银行机构代码
F59: 金融许可证号 | G59: JRXKZH | H59: 10402 | I59: 金融许可证号 | J59: =INDEX(数据元说明!A:F,MATCH(I59,数据元说明!C:C,0),2) -> 001011 | K59: =INDEX(数据元说明!A:F,MATCH(I59,数据元说明!C:C,0),5) -> 金融许可证机构编码编制规则（试行） 一、机构编码结构 机构编码由大写英文字母和数字组成，共15位。分六个部分，分别是机构类型代码、机构代码、组织类别代码、发证机关代码、地址代码、顺序代码，从左至右顺序排列，如下表所示。 二、机构编码含义 （一）第［一］位是机构类型代码，用大写英文字母表示。 A-政策性银行 B-商业银行 C-农村合作银行 D-城市信用社 E-农村信用社 F-资金互助社 J-金融资产管理公司 K-信托公司 L-财务公司 M-金融租赁公司 N-汽车金融公司 P-货币经纪公司 Q-贷款公司 Z-其他类金融机构 新增机构类型时，根据需要确定机构类型代码。 （二）第［二］位至第［五］位是机构代码，用数字表示。 1.每个法人机构指定唯一的代码，由计算机系统按照规则自动生成。除农村信用社、资金互助社、贷款公司（E、F、Q类机构）外，全国统一编码。E、F、Q类机构在省（自治区、直辖市）范围内统一编码。 2.新设立的机构依照所属机构类型顺序排列。 机构代码编码示例如下： A-政策性银行 0001-国家开发银行 …… B-商业银行 0001-中国工商银行股份有限公司 …… C-农村合作银行 0001-天津大港农村合作银行 …… D-城市信用社 0001-邯郸市城市信用社股份有限公司 …… E-农村信用社天津市 0001-天津市宝坻区农村信用合作联社 …… 新疆维吾尔自治区 0001-新疆维吾尔自治区农村信用社联合社 …… F-资金互助社 吉林省 0001-吉林省梨树县闰家村百信农村资金互助社 …… 青海省 0001-青海省乐都县雨润镇兴乐农村资金互助社 …… J-金融资产管理公司 0001-中国华融资产管理公司 …… K-信托投资公司 0001-中诚信托投资有限责任公司 …… L-财务公司 0001-中海石油财务有限责任公司 …… M-金融租赁公司 0001-中国外贸金融租赁公司 …… N-汽车金融公司 0001-大众汽车金融（中国）有限公司 …… P-货币经纪公司 0001-上海国利货币经纪有限公司 …… Q-贷款公司四川省 0001-四川省仪陇县惠民贷款有限责任公司 …… 新疆维吾尔自治区 0001- …… Z-其他类金融机构 0001-中央国债登记结算有限责任公司 …… （三）第〔六〕位是组织类别代码，用大写英文字母表示。 机构类型不同，组织类别代码的含义不同。定义如下： 1.A-政策性银行 H-总行 G-总行营业部 H-级分行 K-一级分行营业部 M-二级分行 S-支行 X-其他分支机构 2.B-商业银行 H-总行 G-总行营业部、专营机构 B-一级分行 K-一级分行营业部 L-二级分行 M-直属支行 N-二级分行营业部 S-支行 U-分理处、办事处、营业所 V-储蓄所 X-其他分支机构 3.C-农村合作银行 H-总行 S-支行 U-分理处 V-储蓄所 X-其他分支机构 4.D-城市信用社 H-法人 S-分社、营业部 X-其他分支机构 5.E-农村信用社 H-省（自治区、直辖市）联合社 B-地（市）联合社、联社 S-县（市）联合社、联社、合作社（县级） T-信用合作社 U-信用社、分社 V-储蓄所 X-其他分支机构 6.F-资金互助社 H-法人 7.J-金融资产管理公司 H-总公司 B-办事处 X-其他分支机构 8.K-信托公司 H-法人 9.N-汽车金融公司 H-法人 10.L-财务公司 H-总公司 B-分公司 X-其他分支机构 11.M-金融租赁公司 H-总公司 B-分公司 X-其他分支机构 12.P-货币经纪公司 H-总公司 B-分公司 X-其他分支机构 13.Q-贷款公司 H-总公司 B-分公司 X-其他分支机构 14.Z-其他类金融机构 Z类机构组织类别代码编码方法参照以上规则。 新增机构类型时，参照以上规则，根据实际情况定义其组织类别代码。 （四）第〔七〕位是发证机关代码，用数字表示。 1-银保监会 2-银监局 3-银监分局 （五）第〔八〕位至第〔十一〕是地址代码，用数字表示。按照《中华人民共和国行政区划代码》 （GB/T2260），取市（地区、自治州、盟）、直辖市行政区划代码前四位，作为地址代码。 地址代码示例如下：1100表示北京市，1200表示天津市，1301表示石家庄市，…… （六）第〔十二〕位至第〔十五〕位是顺序代码，用数字表示。机构类型代码、机构代码、组织类别代码、发证机关代码和地址代码相同的机构按照制发金融许可证的顺序编码。 三、机构编码的编制规则 编制机构编码时，按照从左至右的顺序依次确定机构类型代码、机构代码、组织类别代码、发证机关代码、地址代码、顺序代码，由计算机自动生成。 为了保证机构编码的唯一性，以利于电子计算机较长时间地存储数据，因行政许可变更需换发金融许可证，涉及机构编码变更的，原机构编码不再使用.金融机构终止的，机构编码不再使用。注销开业许可收回金融许可证的，机构编码不再使用。 | L59: =INDEX(数据元说明!A:F,MATCH(I59,数据元说明!C:C,0),6) -> C..30 | M59: 营业机构、管理机构必须填报“金融许可证号”，内设机构、虚拟机构及营业部取上一级管理机构的金融许可证号。 | N59: 修改 | O59: 备注
F60: 内部机构号 | G60: NBJGH | H60: 10403 | I60: 内部机构号 | J60: =INDEX(数据元说明!A:F,MATCH(I60,数据元说明!C:C,0),2) -> 001012 | K60: =INDEX(数据元说明!A:F,MATCH(I60,数据元说明!C:C,0),5) -> 银行内部机构号。应具有标识机构的唯一性。 | L60: =INDEX(数据元说明!A:F,MATCH(I60,数据元说明!C:C,0),6) -> C..30 | M60: PK。关联数据项：机构信息表.内部机构号
F61: 岗位编号 | G61: GWBH | H61: 10404 | I61: 岗位编号 | J61: =INDEX(数据元说明!A:F,MATCH(I61,数据元说明!C:C,0),2) -> 001025 | K61: =INDEX(数据元说明!A:F,MATCH(I61,数据元说明!C:C,0),5) -> 银行自定义。 | L61: =INDEX(数据元说明!A:F,MATCH(I61,数据元说明!C:C,0),6) -> C..60 | M61: PK。 | N61: 修改 | P61: 调整数据项位置
F62: 岗位种类 | G62: GWZL | H62: 10405 | I62: 岗位种类 | J62: =INDEX(数据元说明!A:F,MATCH(I62,数据元说明!C:C,0),2) -> 001026 | K62: =INDEX(数据元说明!A:F,MATCH(I62,数据元说明!C:C,0),5) -> 岗位种类，中文字典或中文描述，银行自定义。 | L62: =INDEX(数据元说明!A:F,MATCH(I62,数据元说明!C:C,0),6) -> C..60 | M62: 外资银行允许用英文描述。
F63: 岗位名称 | G63: GWMC | H63: 10406 | I63: 岗位名称 | J63: =INDEX(数据元说明!A:F,MATCH(I63,数据元说明!C:C,0),2) -> 001027 | K63: =INDEX(数据元说明!A:F,MATCH(I63,数据元说明!C:C,0),5) -> 岗位名称，中文字典或中文描述，银行自定义。 | L63: =INDEX(数据元说明!A:F,MATCH(I63,数据元说明!C:C,0),6) -> C..200 | M63: 外资银行允许用英文描述。
F64: 岗位说明 | G64: GWSM | H64: 10407 | I64: 岗位说明 | J64: =INDEX(数据元说明!A:F,MATCH(I64,数据元说明!C:C,0),2) -> 001028 | K64: =INDEX(数据元说明!A:F,MATCH(I64,数据元说明!C:C,0),5) -> 对岗位工作的中文描述，银行自定义。 | L64: =INDEX(数据元说明!A:F,MATCH(I64,数据元说明!C:C,0),6) -> C..400 | M64: 外资银行允许用英文描述。
F65: 岗位状态 | G65: GWZT | H65: 10408 | I65: 状态 | J65: =INDEX(数据元说明!A:F,MATCH(I65,数据元说明!C:C,0),2) -> 001020 | K65: =INDEX(数据元说明!A:F,MATCH(I65,数据元说明!C:C,0),5) -> 中文字典或中文描述，银行自定义。 | L65: =INDEX(数据元说明!A:F,MATCH(I65,数据元说明!C:C,0),6) -> C..30
F66: 备注 | G66: BBZ | H66: 10409 | I66: 备注 | J66: =INDEX(数据元说明!A:F,MATCH(I66,数据元说明!C:C,0),2) -> 001040 | K66: =INDEX(数据元说明!A:F,MATCH(I66,数据元说明!C:C,0),5) -> 银行自定义。 | L66: =INDEX(数据元说明!A:F,MATCH(I66,数据元说明!C:C,0),6) -> C..600 | M66: 描述其他字段未能详尽说明的情况，如是否是历史数据、未通过校验原因等可在备注栏说明，简述即可，不必详述，不同备注事项用分号或句号分隔开。 | N66: 新增
F67: 采集日期 | G67: CJRQ | H67: 10410 | I67: 日期 | J67: =INDEX(数据元说明!A:F,MATCH(I67,数据元说明!C:C,0),2) -> 001005 | K67: =INDEX(数据元说明!A:F,MATCH(I67,数据元说明!C:C,0),5) -> YYYYMMDD，默认值99991231。 | L67: =INDEX(数据元说明!A:F,MATCH(I67,数据元说明!C:C,0),6) -> C8 | M67: PK。采集日期指该期（批次）数据报送的期末日期，例如：按日采集的表，采集日期应为每日；按月采集的表，采集日期应为月末最后一天；以此类推。有特殊报送要求的，应以报送要求的截至日期为采集日期。
C68: JGGXB | D68: 机构关系表 | E68: 105 | M68: =INDEX(表结构总览!E:H,MATCH(D68,表结构总览!E:E,0),4) -> 机构关系表报送范围应包括所有进行账务处理的机构，至少应包括总行、分行、支行等实体机构和省级汇总、地市级汇总、法人汇总、分行汇总。会计全科目表中的机构在机构关系表中都需要报送，每次全量报送。 | N68: 修改
F69: 银行机构代码 | G69: YHJGDM | H69: 10501 | I69: 银行机构代码 | J69: =INDEX(数据元说明!A:F,MATCH(I69,数据元说明!C:C,0),2) -> 001010 | K69: =INDEX(数据元说明!A:F,MATCH(I69,数据元说明!C:C,0),5) -> 12位人行支付行号或SWIFT行号。 | L69: =INDEX(数据元说明!A:F,MATCH(I69,数据元说明!C:C,0),6) -> C..30 | M69: 关联数据项：机构信息表.银行机构代码 | N69: 修改 | P69: 增加备注说明
F70: 金融许可证号 | G70: JRXKZH | H70: 10502 | I70: 金融许可证号 | J70: =INDEX(数据元说明!A:F,MATCH(I70,数据元说明!C:C,0),2) -> 001011 | K70: =INDEX(数据元说明!A:F,MATCH(I70,数据元说明!C:C,0),5) -> 金融许可证机构编码编制规则（试行） 一、机构编码结构 机构编码由大写英文字母和数字组成，共15位。分六个部分，分别是机构类型代码、机构代码、组织类别代码、发证机关代码、地址代码、顺序代码，从左至右顺序排列，如下表所示。 二、机构编码含义 （一）第［一］位是机构类型代码，用大写英文字母表示。 A-政策性银行 B-商业银行 C-农村合作银行 D-城市信用社 E-农村信用社 F-资金互助社 J-金融资产管理公司 K-信托公司 L-财务公司 M-金融租赁公司 N-汽车金融公司 P-货币经纪公司 Q-贷款公司 Z-其他类金融机构 新增机构类型时，根据需要确定机构类型代码。 （二）第［二］位至第［五］位是机构代码，用数字表示。 1.每个法人机构指定唯一的代码，由计算机系统按照规则自动生成。除农村信用社、资金互助社、贷款公司（E、F、Q类机构）外，全国统一编码。E、F、Q类机构在省（自治区、直辖市）范围内统一编码。 2.新设立的机构依照所属机构类型顺序排列。 机构代码编码示例如下： A-政策性银行 0001-国家开发银行 …… B-商业银行 0001-中国工商银行股份有限公司 …… C-农村合作银行 0001-天津大港农村合作银行 …… D-城市信用社 0001-邯郸市城市信用社股份有限公司 …… E-农村信用社天津市 0001-天津市宝坻区农村信用合作联社 …… 新疆维吾尔自治区 0001-新疆维吾尔自治区农村信用社联合社 …… F-资金互助社 吉林省 0001-吉林省梨树县闰家村百信农村资金互助社 …… 青海省 0001-青海省乐都县雨润镇兴乐农村资金互助社 …… J-金融资产管理公司 0001-中国华融资产管理公司 …… K-信托投资公司 0001-中诚信托投资有限责任公司 …… L-财务公司 0001-中海石油财务有限责任公司 …… M-金融租赁公司 0001-中国外贸金融租赁公司 …… N-汽车金融公司 0001-大众汽车金融（中国）有限公司 …… P-货币经纪公司 0001-上海国利货币经纪有限公司 …… Q-贷款公司四川省 0001-四川省仪陇县惠民贷款有限责任公司 …… 新疆维吾尔自治区 0001- …… Z-其他类金融机构 0001-中央国债登记结算有限责任公司 …… （三）第〔六〕位是组织类别代码，用大写英文字母表示。 机构类型不同，组织类别代码的含义不同。定义如下： 1.A-政策性银行 H-总行 G-总行营业部 H-级分行 K-一级分行营业部 M-二级分行 S-支行 X-其他分支机构 2.B-商业银行 H-总行 G-总行营业部、专营机构 B-一级分行 K-一级分行营业部 L-二级分行 M-直属支行 N-二级分行营业部 S-支行 U-分理处、办事处、营业所 V-储蓄所 X-其他分支机构 3.C-农村合作银行 H-总行 S-支行 U-分理处 V-储蓄所 X-其他分支机构 4.D-城市信用社 H-法人 S-分社、营业部 X-其他分支机构 5.E-农村信用社 H-省（自治区、直辖市）联合社 B-地（市）联合社、联社 S-县（市）联合社、联社、合作社（县级） T-信用合作社 U-信用社、分社 V-储蓄所 X-其他分支机构 6.F-资金互助社 H-法人 7.J-金融资产管理公司 H-总公司 B-办事处 X-其他分支机构 8.K-信托公司 H-法人 9.N-汽车金融公司 H-法人 10.L-财务公司 H-总公司 B-分公司 X-其他分支机构 11.M-金融租赁公司 H-总公司 B-分公司 X-其他分支机构 12.P-货币经纪公司 H-总公司 B-分公司 X-其他分支机构 13.Q-贷款公司 H-总公司 B-分公司 X-其他分支机构 14.Z-其他类金融机构 Z类机构组织类别代码编码方法参照以上规则。 新增机构类型时，参照以上规则，根据实际情况定义其组织类别代码。 （四）第〔七〕位是发证机关代码，用数字表示。 1-银保监会 2-银监局 3-银监分局 （五）第〔八〕位至第〔十一〕是地址代码，用数字表示。按照《中华人民共和国行政区划代码》 （GB/T2260），取市（地区、自治州、盟）、直辖市行政区划代码前四位，作为地址代码。 地址代码示例如下：1100表示北京市，1200表示天津市，1301表示石家庄市，…… （六）第〔十二〕位至第〔十五〕位是顺序代码，用数字表示。机构类型代码、机构代码、组织类别代码、发证机关代码和地址代码相同的机构按照制发金融许可证的顺序编码。 三、机构编码的编制规则 编制机构编码时，按照从左至右的顺序依次确定机构类型代码、机构代码、组织类别代码、发证机关代码、地址代码、顺序代码，由计算机自动生成。 为了保证机构编码的唯一性，以利于电子计算机较长时间地存储数据，因行政许可变更需换发金融许可证，涉及机构编码变更的，原机构编码不再使用.金融机构终止的，机构编码不再使用。注销开业许可收回金融许可证的，机构编码不再使用。 | L70: =INDEX(数据元说明!A:F,MATCH(I70,数据元说明!C:C,0),6) -> C..30 | M70: 营业机构、管理机构必须填报“金融许可证号”，内设机构、虚拟机构及营业部取上一级管理机构的金融许可证号。 | N70: 修改 | O70: 备注
F71: 内部机构号 | G71: NBJGH | H71: 10503 | I71: 内部机构号 | J71: =INDEX(数据元说明!A:F,MATCH(I71,数据元说明!C:C,0),2) -> 001012 | K71: =INDEX(数据元说明!A:F,MATCH(I71,数据元说明!C:C,0),5) -> 银行内部机构号。应具有标识机构的唯一性。 | L71: =INDEX(数据元说明!A:F,MATCH(I71,数据元说明!C:C,0),6) -> C..30 | M71: PK
F72: 银行机构名称 | G72: YHJGMC | H72: 10504 | I72: 名称 | J72: =INDEX(数据元说明!A:F,MATCH(I72,数据元说明!C:C,0),2) -> 001001 | K72: =INDEX(数据元说明!A:F,MATCH(I72,数据元说明!C:C,0),5) -> 名称应与公章所使用的名称完全一致。银行机构以银保监会金融机构许可证登记名称为准。无独立金融机构许可证的机构，可在本名称中体现出机构特征。第三方支付平台填报第三方支付平台名称。 客户名称按照客户的不同类型按如下标准填报。 （1）集团客户，填报银行对该集团授信采用的集团客户名称。视同集团客户填报的供应链融资填报核心企业客户名称。 （2）单一法人客户，经有关部门批准正式使用的全称，与公章所使用的名称完全一致。视同单一法人客户填报的分公司，填报分公司全称，与分公司公章所使用的名称完全一致。客户是境内涉密机构的，客户名称填报为“*********”。 （3）同业客户，经有关部门批准正式使用的客户全称，与客户公章所使用的名称完全一致。 （4）自然人，与有效证件上的姓名一致。 （5）境外客户，客户名称应尽量以中文翻译填报，如没有可填报英文名称。 | L72: =INDEX(数据元说明!A:F,MATCH(I72,数据元说明!C:C,0),6) -> C..400 | M72: 需填写全称，有金融许可证号的需与金融许可证上的机构名称保持一致。关联数据项：机构信息表.银行机构名称 | N72: 修改 | O72: 格式 | P72: 增加备注说明
F73: 上级管理机构代码 | G73: SJGLJGDM | H73: 10505 | I73: 银行机构代码 | J73: =INDEX(数据元说明!A:F,MATCH(I73,数据元说明!C:C,0),2) -> 001010 | K73: =INDEX(数据元说明!A:F,MATCH(I73,数据元说明!C:C,0),5) -> 12位人行支付行号或SWIFT行号。 | L73: =INDEX(数据元说明!A:F,MATCH(I73,数据元说明!C:C,0),6) -> C..30 | M73: 没有上级机构的该项填写为0，其中总行本级上级机构代码为总行法人。 | N73: 修改 | O73: 数据元
F74: 上级管理内部机构号 | G74: SJGLNBJGH | H74: 10506 | I74: 内部机构号 | J74: =INDEX(数据元说明!A:F,MATCH(I74,数据元说明!C:C,0),2) -> 001012 | K74: =INDEX(数据元说明!A:F,MATCH(I74,数据元说明!C:C,0),5) -> 银行内部机构号。应具有标识机构的唯一性。 | L74: =INDEX(数据元说明!A:F,MATCH(I74,数据元说明!C:C,0),6) -> C..30 | M74: 没有上级机构的该项填写为0，其中总行本级上级机构号为总行法人。 | N74: 新增
F75: 上级管理机构名称 | G75: SJGLJGMC | H75: 10507 | I75: 名称 | J75: =INDEX(数据元说明!A:F,MATCH(I75,数据元说明!C:C,0),2) -> 001001 | K75: =INDEX(数据元说明!A:F,MATCH(I75,数据元说明!C:C,0),5) -> 名称应与公章所使用的名称完全一致。银行机构以银保监会金融机构许可证登记名称为准。无独立金融机构许可证的机构，可在本名称中体现出机构特征。第三方支付平台填报第三方支付平台名称。 客户名称按照客户的不同类型按如下标准填报。 （1）集团客户，填报银行对该集团授信采用的集团客户名称。视同集团客户填报的供应链融资填报核心企业客户名称。 （2）单一法人客户，经有关部门批准正式使用的全称，与公章所使用的名称完全一致。视同单一法人客户填报的分公司，填报分公司全称，与分公司公章所使用的名称完全一致。客户是境内涉密机构的，客户名称填报为“*********”。 （3）同业客户，经有关部门批准正式使用的客户全称，与客户公章所使用的名称完全一致。 （4）自然人，与有效证件上的姓名一致。 （5）境外客户，客户名称应尽量以中文翻译填报，如没有可填报英文名称。 | L75: =INDEX(数据元说明!A:F,MATCH(I75,数据元说明!C:C,0),6) -> C..400 | M75: 没有上级机构的该项填写为空，其中总行本级上级机构为总行法人。 | N75: 修改 | O75: 格式、备注
F76: 备注 | G76: BBZ | H76: 10508 | I76: 备注 | J76: =INDEX(数据元说明!A:F,MATCH(I76,数据元说明!C:C,0),2) -> 001040 | K76: =INDEX(数据元说明!A:F,MATCH(I76,数据元说明!C:C,0),5) -> 银行自定义。 | L76: =INDEX(数据元说明!A:F,MATCH(I76,数据元说明!C:C,0),6) -> C..600 | M76: 描述其他字段未能详尽说明的情况，如是否是历史数据、未通过校验原因等可在备注栏说明，简述即可，不必详述，不同备注事项用分号或句号分隔开。 | N76: 新增
F77: 采集日期 | G77: CJRQ | H77: 10509 | I77: 日期 | J77: =INDEX(数据元说明!A:F,MATCH(I77,数据元说明!C:C,0),2) -> 001005 | K77: =INDEX(数据元说明!A:F,MATCH(I77,数据元说明!C:C,0),5) -> YYYYMMDD，默认值99991231。 | L77: =INDEX(数据元说明!A:F,MATCH(I77,数据元说明!C:C,0),6) -> C8 | M77: PK。采集日期指该期（批次）数据报送的期末日期，例如：按日采集的表，采集日期应为每日；按月采集的表，采集日期应为月末最后一天；以此类推。有特殊报送要求的，应以报送要求的截至日期为采集日期。
C78: GDXXB | D78: 股东信息表 | E78: 106 | M78: =INDEX(表结构总览!E:H,MATCH(D78,表结构总览!E:E,0),4) -> 本表应填报银行自身的股东。对于已上市银行，需填报持有或控制1%以上股份或表决权，及虽不足1%但对商业银行经营管理有重大影响的股东。未上市银行机构应报送所有的对公、个人股东信息。 | N78: 修改
F79: 银行机构代码 | G79: YHJGDM | H79: 10601 | I79: 银行机构代码 | J79: =INDEX(数据元说明!A:F,MATCH(I79,数据元说明!C:C,0),2) -> 001010 | K79: =INDEX(数据元说明!A:F,MATCH(I79,数据元说明!C:C,0),5) -> 12位人行支付行号或SWIFT行号。 | L79: =INDEX(数据元说明!A:F,MATCH(I79,数据元说明!C:C,0),6) -> C..30 | M79: 填报本行法人机构代码。关联数据项：机构信息表.银行机构代码
F80: 银行机构名称 | G80: YHJGMC | H80: 10602 | I80: 名称 | J80: =INDEX(数据元说明!A:F,MATCH(I80,数据元说明!C:C,0),2) -> 001001 | K80: =INDEX(数据元说明!A:F,MATCH(I80,数据元说明!C:C,0),5) -> 名称应与公章所使用的名称完全一致。银行机构以银保监会金融机构许可证登记名称为准。无独立金融机构许可证的机构，可在本名称中体现出机构特征。第三方支付平台填报第三方支付平台名称。 客户名称按照客户的不同类型按如下标准填报。 （1）集团客户，填报银行对该集团授信采用的集团客户名称。视同集团客户填报的供应链融资填报核心企业客户名称。 （2）单一法人客户，经有关部门批准正式使用的全称，与公章所使用的名称完全一致。视同单一法人客户填报的分公司，填报分公司全称，与分公司公章所使用的名称完全一致。客户是境内涉密机构的，客户名称填报为“*********”。 （3）同业客户，经有关部门批准正式使用的客户全称，与客户公章所使用的名称完全一致。 （4）自然人，与有效证件上的姓名一致。 （5）境外客户，客户名称应尽量以中文翻译填报，如没有可填报英文名称。 | L80: =INDEX(数据元说明!A:F,MATCH(I80,数据元说明!C:C,0),6) -> C..400 | M80: 填报本行法人机构名称。关联数据项：机构信息表.银行机构名称 | N80: 修改 | O80: 格式 | P80: 增加备注说明
F81: 客户统一编号 | G81: KHTYBH | H81: 10603 | I81: 客户统一编号 | J81: =INDEX(数据元说明!A:F,MATCH(I81,数据元说明!C:C,0),2) -> 002001 | K81: =INDEX(数据元说明!A:F,MATCH(I81,数据元说明!C:C,0),5) -> 银行自定义的唯一识别客户的标识。供应链融资的填写供应链融资编码。 | L81: =INDEX(数据元说明!A:F,MATCH(I81,数据元说明!C:C,0),6) -> C..60 | M81: 如果股东不是本银行客户，填为空值。 | N81: 修改 | P81: 调整数据项位置
F82: 股东名称 | G82: GDMC | H82: 10604 | I82: 名称 | J82: =INDEX(数据元说明!A:F,MATCH(I82,数据元说明!C:C,0),2) -> 001001 | K82: =INDEX(数据元说明!A:F,MATCH(I82,数据元说明!C:C,0),5) -> 名称应与公章所使用的名称完全一致。银行机构以银保监会金融机构许可证登记名称为准。无独立金融机构许可证的机构，可在本名称中体现出机构特征。第三方支付平台填报第三方支付平台名称。 客户名称按照客户的不同类型按如下标准填报。 （1）集团客户，填报银行对该集团授信采用的集团客户名称。视同集团客户填报的供应链融资填报核心企业客户名称。 （2）单一法人客户，经有关部门批准正式使用的全称，与公章所使用的名称完全一致。视同单一法人客户填报的分公司，填报分公司全称，与分公司公章所使用的名称完全一致。客户是境内涉密机构的，客户名称填报为“*********”。 （3）同业客户，经有关部门批准正式使用的客户全称，与客户公章所使用的名称完全一致。 （4）自然人，与有效证件上的姓名一致。 （5）境外客户，客户名称应尽量以中文翻译填报，如没有可填报英文名称。 | L82: =INDEX(数据元说明!A:F,MATCH(I82,数据元说明!C:C,0),6) -> C..400 | M82: PK。股东名称：对个人股东，为股东姓名；对法人股东，为股东经有关部门批准正式使用的客户全称，与客户公章所使用的名称完全一致。股东顺序按持股比例确定。非隐私，不做变形。 | N82: 修改 | O82: 格式
F83: 股东类型 | G83: GDLX | H83: 10605 | I83: 股东类别 | J83: =INDEX(数据元说明!A:F,MATCH(I83,数据元说明!C:C,0),2) -> 002027 | K83: =INDEX(数据元说明!A:F,MATCH(I83,数据元说明!C:C,0),5) -> 自然人，纯国有企业，国有控股企业，国有参股企业，民营企业，政府机关，事业单位，社会团体，境外机构，其他-银行自定义。无法以枚举类型填报的，以“其他-XX”填报，其中“XX”为银行自定义类型。 | L83: =INDEX(数据元说明!A:F,MATCH(I83,数据元说明!C:C,0),6) -> C..60 | N83: 新增
F84: 股东证件类别 | G84: GDZJLB | H84: 10606 | I84: 证件类别 | J84: =INDEX(数据元说明!A:F,MATCH(I84,数据元说明!C:C,0),2) -> 002002 | K84: =INDEX(数据元说明!A:F,MATCH(I84,数据元说明!C:C,0),5) -> 同业客户：银行机构代码，金融许可证号，SWIFT编码，其他-XX。 对公客户：统一社会信用代码，组织机构代码，营业执照（工商注册号），公司注册证书，全球法人识别码，其他-XX。 个人客户：居民身份证，军官证，文职干部证，警官证，士兵证，户口簿，临时身份证，其他有效通行旅行证件，护照，学生证，无证件，其他-XX。 无法以枚举类型填报的，以“其他-XX”报送，其中“XX”为银行自定义类型。 对公客户优先填报统一社会信用代码，没有统一社会信用代码的对公客户填报组织机构代码。组织机构代码、统一社会信用代码均没有的可以填报客户提供的批文文号、开户主证件、上级机构统一社会信用代码等，以“其他-XX”填报。 | L84: =INDEX(数据元说明!A:F,MATCH(I84,数据元说明!C:C,0),6) -> C..60 | M84: 不可为空。如未收集证件号码，可以填写为其他任意能识别该股东的编号,如“其他-客户编号”。 | N84: 修改 | O84: 数据元说明
F85: 股东证件号码 | G85: GDZJHM | H85: 10607 | I85: 证件号码 | J85: =INDEX(数据元说明!A:F,MATCH(I85,数据元说明!C:C,0),2) -> 002003 | K85: =INDEX(数据元说明!A:F,MATCH(I85,数据元说明!C:C,0),5) -> 与证件类别对应的证件号码。涉及个人身份证件时需按照本规范给定规则进行脱敏处理。 | L85: =INDEX(数据元说明!A:F,MATCH(I85,数据元说明!C:C,0),6) -> C..70 | M85: 如包含个人身份证件号码，则为隐私，银行机构需做变形，变形规则见《采集技术接口说明》。 | N85: 修改 | O85: 格式
F86: 持股数量 | G86: CGSL | H86: 10608 | I86: 数量 | J86: =INDEX(数据元说明!A:F,MATCH(I86,数据元说明!C:C,0),2) -> 001032 | K86: =INDEX(数据元说明!A:F,MATCH(I86,数据元说明!C:C,0),5) -> 数量。 | L86: =INDEX(数据元说明!A:F,MATCH(I86,数据元说明!C:C,0),6) -> D20 | M86: 股东持有银行股数，以股为单位。填报机构为非股份法人的可以为空。 | N86: 新增
F87: 持股比例 | G87: CGBL | H87: 10609 | I87: 比例（精） | J87: =INDEX(数据元说明!A:F,MATCH(I87,数据元说明!C:C,0),2) -> 001004 | K87: =INDEX(数据元说明!A:F,MATCH(I87,数据元说明!C:C,0),5) -> 百分比为单位，即1/100，保留六位小数。4.123456%则填报为4.123456。 | L87: =INDEX(数据元说明!A:F,MATCH(I87,数据元说明!C:C,0),6) -> D20.6 | M87: PK。 | N87: 修改 | O87: 数据元
F88: 入股日期 | G88: RGRQ | H88: 10610 | I88: 日期 | J88: =INDEX(数据元说明!A:F,MATCH(I88,数据元说明!C:C,0),2) -> 001005 | K88: =INDEX(数据元说明!A:F,MATCH(I88,数据元说明!C:C,0),5) -> YYYYMMDD，默认值99991231。 | L88: =INDEX(数据元说明!A:F,MATCH(I88,数据元说明!C:C,0),6) -> C8 | M88: 最近一次持股份额由0变为非0的日期。 | N88: 修改 | O88: 数据项名称、数据项代码
F89: 质押比例 | G89: ZYBL | H89: 10611 | I89: 比例（精） | J89: =INDEX(数据元说明!A:F,MATCH(I89,数据元说明!C:C,0),2) -> 001004 | K89: =INDEX(数据元说明!A:F,MATCH(I89,数据元说明!C:C,0),5) -> 百分比为单位，即1/100，保留六位小数。4.123456%则填报为4.123456。 | L89: =INDEX(数据元说明!A:F,MATCH(I89,数据元说明!C:C,0),6) -> D20.6 | M89: 填报该股东截至报送日股权质押的比例，质押比例分母为股东持有股份数量。未质押股权的填0，未采集质押比例的填报为空。 | N89: 新增
F90: 是否驻派董监事 | G90: SFZPDJS | H90: 10612 | I90: 是否标志 | J90: =INDEX(数据元说明!A:F,MATCH(I90,数据元说明!C:C,0),2) -> 001002 | K90: =INDEX(数据元说明!A:F,MATCH(I90,数据元说明!C:C,0),5) -> 是，否。 | L90: =INDEX(数据元说明!A:F,MATCH(I90,数据元说明!C:C,0),6) -> C3 | M90: 该股东是否为银行机构的驻派董事、监事。 | N90: 新增
F91: 股东状态 | G91: GDZT | H91: 10613 | I91: 有效状态 | J91: =INDEX(数据元说明!A:F,MATCH(I91,数据元说明!C:C,0),2) -> 007005 | K91: =INDEX(数据元说明!A:F,MATCH(I91,数据元说明!C:C,0),5) -> 有效，无效。 | L91: =INDEX(数据元说明!A:F,MATCH(I91,数据元说明!C:C,0),6) -> C6 | M91: 表示一条记录是否已经无效。默认为有效，当需要删除一条股东信息时，更新为无效。 | N91: 修改 | O91: 数据元说明
F92: 最近一次变动日期 | G92: ZJYCBDRQ | H92: 10614 | I92: 日期 | J92: =INDEX(数据元说明!A:F,MATCH(I92,数据元说明!C:C,0),2) -> 001005 | K92: =INDEX(数据元说明!A:F,MATCH(I92,数据元说明!C:C,0),5) -> YYYYMMDD，默认值99991231。 | L92: =INDEX(数据元说明!A:F,MATCH(I92,数据元说明!C:C,0),6) -> C8 | M92: 报送最近一次入股、增资扩股或股权转让等影响持股比例的日期。 | N92: 新增
F93: 备注 | G93: BBZ | H93: 10615 | I93: 备注 | J93: =INDEX(数据元说明!A:F,MATCH(I93,数据元说明!C:C,0),2) -> 001040 | K93: =INDEX(数据元说明!A:F,MATCH(I93,数据元说明!C:C,0),5) -> 银行自定义。 | L93: =INDEX(数据元说明!A:F,MATCH(I93,数据元说明!C:C,0),6) -> C..600 | M93: 描述其他字段未能详尽说明的情况，如是否是历史数据、未通过校验原因等可在备注栏说明，简述即可，不必详述，不同备注事项用分号或句号分隔开。 | N93: 新增
F94: 采集日期 | G94: CJRQ | H94: 10616 | I94: 日期 | J94: =INDEX(数据元说明!A:F,MATCH(I94,数据元说明!C:C,0),2) -> 001005 | K94: =INDEX(数据元说明!A:F,MATCH(I94,数据元说明!C:C,0),5) -> YYYYMMDD，默认值99991231。 | L94: =INDEX(数据元说明!A:F,MATCH(I94,数据元说明!C:C,0),6) -> C8 | M94: PK。采集日期指该期（批次）数据报送的期末日期，例如：按日采集的表，采集日期应为每日；按月采集的表，采集日期应为月末最后一天；以此类推。有特殊报送要求的，应以报送要求的截至日期为采集日期。
A95: 客户信息 | B95: 002
C96: GRJCXXB | D96: 个人基础信息表 | E96: 201 | M96: =INDEX(表结构总览!E:H,MATCH(D96,表结构总览!E:E,0),4) -> 个人基础信息，包括本行客户及本行客户的担保、配偶、亲属关系所涉及到的个人客户信息。不再列为银行客户的数据不报送，存续业务中的所有个人信息都报送。。 | N96: 修改 | O96: 备注
F97: 银行机构代码 | G97: YHJGDM | H97: 20101 | I97: 银行机构代码 | J97: =INDEX(数据元说明!A:F,MATCH(I97,数据元说明!C:C,0),2) -> 001010 | K97: =INDEX(数据元说明!A:F,MATCH(I97,数据元说明!C:C,0),5) -> 12位人行支付行号或SWIFT行号。 | L97: =INDEX(数据元说明!A:F,MATCH(I97,数据元说明!C:C,0),6) -> C..30 | M97: 填报客户归属的银行机构。关联数据项：机构信息表.银行机构代码
F98: 金融许可证号 | G98: JRXKZH | H98: 20102 | I98: 金融许可证号 | J98: =INDEX(数据元说明!A:F,MATCH(I98,数据元说明!C:C,0),2) -> 001011 | K98: =INDEX(数据元说明!A:F,MATCH(I98,数据元说明!C:C,0),5) -> 金融许可证机构编码编制规则（试行） 一、机构编码结构 机构编码由大写英文字母和数字组成，共15位。分六个部分，分别是机构类型代码、机构代码、组织类别代码、发证机关代码、地址代码、顺序代码，从左至右顺序排列，如下表所示。 二、机构编码含义 （一）第［一］位是机构类型代码，用大写英文字母表示。 A-政策性银行 B-商业银行 C-农村合作银行 D-城市信用社 E-农村信用社 F-资金互助社 J-金融资产管理公司 K-信托公司 L-财务公司 M-金融租赁公司 N-汽车金融公司 P-货币经纪公司 Q-贷款公司 Z-其他类金融机构 新增机构类型时，根据需要确定机构类型代码。 （二）第［二］位至第［五］位是机构代码，用数字表示。 1.每个法人机构指定唯一的代码，由计算机系统按照规则自动生成。除农村信用社、资金互助社、贷款公司（E、F、Q类机构）外，全国统一编码。E、F、Q类机构在省（自治区、直辖市）范围内统一编码。 2.新设立的机构依照所属机构类型顺序排列。 机构代码编码示例如下： A-政策性银行 0001-国家开发银行 …… B-商业银行 0001-中国工商银行股份有限公司 …… C-农村合作银行 0001-天津大港农村合作银行 …… D-城市信用社 0001-邯郸市城市信用社股份有限公司 …… E-农村信用社天津市 0001-天津市宝坻区农村信用合作联社 …… 新疆维吾尔自治区 0001-新疆维吾尔自治区农村信用社联合社 …… F-资金互助社 吉林省 0001-吉林省梨树县闰家村百信农村资金互助社 …… 青海省 0001-青海省乐都县雨润镇兴乐农村资金互助社 …… J-金融资产管理公司 0001-中国华融资产管理公司 …… K-信托投资公司 0001-中诚信托投资有限责任公司 …… L-财务公司 0001-中海石油财务有限责任公司 …… M-金融租赁公司 0001-中国外贸金融租赁公司 …… N-汽车金融公司 0001-大众汽车金融（中国）有限公司 …… P-货币经纪公司 0001-上海国利货币经纪有限公司 …… Q-贷款公司四川省 0001-四川省仪陇县惠民贷款有限责任公司 …… 新疆维吾尔自治区 0001- …… Z-其他类金融机构 0001-中央国债登记结算有限责任公司 …… （三）第〔六〕位是组织类别代码，用大写英文字母表示。 机构类型不同，组织类别代码的含义不同。定义如下： 1.A-政策性银行 H-总行 G-总行营业部 H-级分行 K-一级分行营业部 M-二级分行 S-支行 X-其他分支机构 2.B-商业银行 H-总行 G-总行营业部、专营机构 B-一级分行 K-一级分行营业部 L-二级分行 M-直属支行 N-二级分行营业部 S-支行 U-分理处、办事处、营业所 V-储蓄所 X-其他分支机构 3.C-农村合作银行 H-总行 S-支行 U-分理处 V-储蓄所 X-其他分支机构 4.D-城市信用社 H-法人 S-分社、营业部 X-其他分支机构 5.E-农村信用社 H-省（自治区、直辖市）联合社 B-地（市）联合社、联社 S-县（市）联合社、联社、合作社（县级） T-信用合作社 U-信用社、分社 V-储蓄所 X-其他分支机构 6.F-资金互助社 H-法人 7.J-金融资产管理公司 H-总公司 B-办事处 X-其他分支机构 8.K-信托公司 H-法人 9.N-汽车金融公司 H-法人 10.L-财务公司 H-总公司 B-分公司 X-其他分支机构 11.M-金融租赁公司 H-总公司 B-分公司 X-其他分支机构 12.P-货币经纪公司 H-总公司 B-分公司 X-其他分支机构 13.Q-贷款公司 H-总公司 B-分公司 X-其他分支机构 14.Z-其他类金融机构 Z类机构组织类别代码编码方法参照以上规则。 新增机构类型时，参照以上规则，根据实际情况定义其组织类别代码。 （四）第〔七〕位是发证机关代码，用数字表示。 1-银保监会 2-银监局 3-银监分局 （五）第〔八〕位至第〔十一〕是地址代码，用数字表示。按照《中华人民共和国行政区划代码》 （GB/T2260），取市（地区、自治州、盟）、直辖市行政区划代码前四位，作为地址代码。 地址代码示例如下：1100表示北京市，1200表示天津市，1301表示石家庄市，…… （六）第〔十二〕位至第〔十五〕位是顺序代码，用数字表示。机构类型代码、机构代码、组织类别代码、发证机关代码和地址代码相同的机构按照制发金融许可证的顺序编码。 三、机构编码的编制规则 编制机构编码时，按照从左至右的顺序依次确定机构类型代码、机构代码、组织类别代码、发证机关代码、地址代码、顺序代码，由计算机自动生成。 为了保证机构编码的唯一性，以利于电子计算机较长时间地存储数据，因行政许可变更需换发金融许可证，涉及机构编码变更的，原机构编码不再使用.金融机构终止的，机构编码不再使用。注销开业许可收回金融许可证的，机构编码不再使用。 | L98: =INDEX(数据元说明!A:F,MATCH(I98,数据元说明!C:C,0),6) -> C..30 | M98: 填报客户归属的银行机构。营业机构、管理机构必须填报“金融许可证号”，内设机构、虚拟机构及营业部取上一级管理机构的金融许可证号。 | N98: 修改 | O98: 备注
F99: 内部机构号 | G99: NBJGH | H99: 20103 | I99: 内部机构号 | J99: =INDEX(数据元说明!A:F,MATCH(I99,数据元说明!C:C,0),2) -> 001012 | K99: =INDEX(数据元说明!A:F,MATCH(I99,数据元说明!C:C,0),5) -> 银行内部机构号。应具有标识机构的唯一性。 | L99: =INDEX(数据元说明!A:F,MATCH(I99,数据元说明!C:C,0),6) -> C..30 | M99: 填报客户归属的银行机构。关联数据项：机构信息表.内部机构号
F100: 银行机构名称 | G100: YHJGMC | H100: 20104 | I100: 名称 | J100: =INDEX(数据元说明!A:F,MATCH(I100,数据元说明!C:C,0),2) -> 001001 | K100: =INDEX(数据元说明!A:F,MATCH(I100,数据元说明!C:C,0),5) -> 名称应与公章所使用的名称完全一致。银行机构以银保监会金融机构许可证登记名称为准。无独立金融机构许可证的机构，可在本名称中体现出机构特征。第三方支付平台填报第三方支付平台名称。 客户名称按照客户的不同类型按如下标准填报。 （1）集团客户，填报银行对该集团授信采用的集团客户名称。视同集团客户填报的供应链融资填报核心企业客户名称。 （2）单一法人客户，经有关部门批准正式使用的全称，与公章所使用的名称完全一致。视同单一法人客户填报的分公司，填报分公司全称，与分公司公章所使用的名称完全一致。客户是境内涉密机构的，客户名称填报为“*********”。 （3）同业客户，经有关部门批准正式使用的客户全称，与客户公章所使用的名称完全一致。 （4）自然人，与有效证件上的姓名一致。 （5）境外客户，客户名称应尽量以中文翻译填报，如没有可填报英文名称。 | L100: =INDEX(数据元说明!A:F,MATCH(I100,数据元说明!C:C,0),6) -> C..400 | M100: 填报客户归属的银行机构。关联数据项：机构信息表.银行机构名称 | N100: 新增
F101: 客户统一编号 | G101: KHTYBH | H101: 20105 | I101: 客户统一编号 | J101: =INDEX(数据元说明!A:F,MATCH(I101,数据元说明!C:C,0),2) -> 002001 | K101: =INDEX(数据元说明!A:F,MATCH(I101,数据元说明!C:C,0),5) -> 银行自定义的唯一识别客户的标识。供应链融资的填写供应链融资编码。 | L101: =INDEX(数据元说明!A:F,MATCH(I101,数据元说明!C:C,0),6) -> C..60 | M101: PK。如包含个人身份证件号码，则为隐私，银行机构需做变形，变形规则见《采集技术接口说明》。 | N101: 修改 | P101: 调整数据项位置
F102: 客户姓名 | G102: KHXM | H102: 20106 | I102: 姓名 | J102: =INDEX(数据元说明!A:F,MATCH(I102,数据元说明!C:C,0),2) -> 001017 | K102: =INDEX(数据元说明!A:F,MATCH(I102,数据元说明!C:C,0),5) -> 姓名。 | L102: =INDEX(数据元说明!A:F,MATCH(I102,数据元说明!C:C,0),6) -> C..200 | M102: 隐私，银行机构变形，变形规则见《采集技术接口说明》。 | N102: 修改 | O102: 备注
F103: 证件类别 | G103: ZJLB | H103: 20107 | I103: 证件类别 | J103: =INDEX(数据元说明!A:F,MATCH(I103,数据元说明!C:C,0),2) -> 002002 | K103: =INDEX(数据元说明!A:F,MATCH(I103,数据元说明!C:C,0),5) -> 同业客户：银行机构代码，金融许可证号，SWIFT编码，其他-XX。 对公客户：统一社会信用代码，组织机构代码，营业执照（工商注册号），公司注册证书，全球法人识别码，其他-XX。 个人客户：居民身份证，军官证，文职干部证，警官证，士兵证，户口簿，临时身份证，其他有效通行旅行证件，护照，学生证，无证件，其他-XX。 无法以枚举类型填报的，以“其他-XX”报送，其中“XX”为银行自定义类型。 对公客户优先填报统一社会信用代码，没有统一社会信用代码的对公客户填报组织机构代码。组织机构代码、统一社会信用代码均没有的可以填报客户提供的批文文号、开户主证件、上级机构统一社会信用代码等，以“其他-XX”填报。 | L103: =INDEX(数据元说明!A:F,MATCH(I103,数据元说明!C:C,0),6) -> C..60
...

Sheet 自营报送范围
A1: 自营资金业务报送范围
A3: 业务大类 | B3: 业务中类 | C3: 业务小类
A4: 同业往来 | B4: 买入返售 | C4: 买入返售证券
C5: 买入返售债权
C6: 买入返售信贷资产
C7: 其他-银行自定义
B8: 卖出回购 | C8: 卖出回购证券
C9: 卖出回购债权
C10: 卖出回购信贷资产
C11: 其他-银行自定义
B12: 拆入 | C12: 拆入银行金融机构
C13: 拆入非银行金融机构
B14: 拆出 | C14: 拆出银行金融机构
C15: 拆出非银行金融机构
B16: 同业借款 | C16: 境内同业借款
C17: 境外同业借款
B18: 同业代付 | C18: 代理境内同业付款
C19: 代理境外同业付款
B20: 存放同业 | C20: 非结算性存放同业
C21: 结算性存放同业
B22: 同业存单 | C22: 同业存单发行
C23: 同业存单投资
B24: 债券发行 | C24: 商业银行债
C25: 银行次级债
C26: 银行永续债
C27: 其他-银行自定义
B28: 其他 | C28: 债券借贷
C29: 银行自定义
A30: 债券投资与同业投资 | B30: 债券投资 | C30: 国债
C31: 地方政府债
C32: 央票
C33: 政府支持机构债
C34: 政策性金融债
C35: 商业性金融债
C36: 非金融企业债券
C37: 资产支持证券（信贷资产证券化）
C38: 资产支持证券（交易所资产支持证券）
C39: 资产支持证券（资产支持票据）
C40: 外国债券
C41: 其他-银行自定义
B42: 权益类投资 | C42: 长期股权投资
C43: 上市股票
C44: 非上市股权
C45: 其他-银行自定义
B46: 公募基金投资 | C46: 债券基金
C47: 货币市场基金
C48: 股票基金
C49: 基金中基金
C50: 混合基金
C51: 其他-银行自定义
B52: 私募基金投资 | C52: 私募证券投资基金
C53: 私募股权投资基金
C54: 私募创业投资基金
C55: 其他-银行自定义
B56: 资产管理产品投资 | C56: 非保本理财投资
C57: 信托产品（资金信托）
C58: 信托产品（财产权信托）
C59: 证券业资产管理产品（不含公募基金）
C60: 保险业资产管理产品
C61: 其他-银行自定义
B62: 其他投资 | C62: 其他债权融资（其他交易平台债权融资工具）
C63: 其他债权融资（非标转标资产）
C64: 贵金属交易
C65: 外汇交易
C66: 商品类交易
C67: 其他-银行自定义
A68: 衍生品交易 | B68: 利率类产品、汇率类产品、商品及其他类产品、股权相关产品、信用类产品、贵金属类产品、复合类产品 | C68: 买入期权，卖出期权，期货合约，远期合约，互换合约，混合类合约。

Sheet 删除的表和数据项
A1: 数据表和数据项删除情况一览表
A3: 传输文件名称 | B3: 表名 | C3: 数据项名称 | D3: 数据项代码 | E3: 数据元 | F3: 数据元编码 | G3: 数据元说明 | H3: 格式 | I3: 变更类型 | J3: 变更原因
B5: 所有明细记录表（9张）
C6: 核心交易流水号、子交易流水号、笔次序号 | I6: 删除数据项 | J6: 不同银行机构的核心系统定义不同，无法与这三个数据项完全对应。使用“时间戳”数据项（19位）（如：时间戳(纳秒)：1530027865231834600），来标识交易序列，代替“流水号”。
C7: 开户行机构号 | D7: KHHJGH | E7: 内部机构号 | F7: 001011 | G7: 银行内部机构号。应具有标识机构的唯一性。 | H7: C..30 | I7: 删除数据项 | J7: 与“内部机构号”重复
B8: 信贷合同表、信贷借据表、贷款展期
C9: 基准利率 | D9: JZLL | E9: 基准利率 | F9: 010030 | G9: 百分比为单位，即1/100，一般为年利。 | H9: D10.6 | I9: 删除数据项 | J9: 现在统一用“实际利率”来表示
C10: 利率浮动 | D10: LLFD | E10: 利率浮动 | F10: 005003 | G10: 基准点为单位。浮动比例与上浮比例均折算点数填报。如上浮1%是填100.00，下浮1%是填-100.00，精确到小数点后2位。如果利率类型是固定利率，则利率浮动填写0.00。如利率类型是浮动利率，则与利率基准结合进行计算。 | H10: D8.5 | I10: 删除数据项 | J10: 现在统一用“实际利率”来表示
C11: 是否LPR | D11: SFLPR | E11: 是否标志 | F11: 001002 | G11: 是，否。 | H11: C..4 | I11: 删除数据项 | J11: “利率类型”修改为：LPR，非LPR
A12: JGXXB | B12: 机构信息表
C13: 机构工作开始时间 | D13: JGGZKSSJ | E13: 时间 | F13: 001007 | G13: 24小时制时间，精确到秒。hhmmss，默认值000000。 | H13: C20 | I13: 删除数据项 | J13: 非监管关注重点
C14: 机构工作终止时间 | D14: JGGZZZSJ | E14: 时间 | F14: 001007 | G14: 24小时制时间，精确到秒。hhmmss，默认值000000。 | H14: C20 | I14: 删除数据项 | J14: 非监管关注重点
C15: 邮政编码 | D15: YZBM | E15: 邮政编码 | F15: 001013 | G15: 该机构注册地邮政编码，6位。超过6位的只取前6位。 | H15: C6 | I15: 删除数据项 | J15: 新增了行政区划代码数据项
C16: 网点号 | D16: WDH | E16: 网点号 | F16: 001014 | G16: 银行内部机构号。 | H16: C..30 | I16: 删除数据项 | J16: 已有内部机构号
A17: YGB | B17: 员工表
C18: 职务 | D18: ZW | E18: 职务 | F18: 001019 | G18: 中文字典或中文描述，银行自定义。 | H18: C..60 | I18: 删除数据项 | J18: 已有岗位编号和岗位名称
C19: 网点号 | D19: WDH | E19: 网点号 | F19: 001014 | G19: 银行内部机构号。 | H19: C..30 | I19: 删除数据项 | J19: 已有内部机构号
A20: GDXX | B20: 股东信息
C21: 实控人姓名 | D21: SKRXM | E21: 姓名 | F21: 001016 | G21: 姓名。 | H21: C..100 | I21: 删除数据项 | J21: 银行自身实控人，无需每条都报送。
C22: 实控人证件类别 | D22: SKRZJLB | E22: 证件类别 | F22: 002002 | G22: 对公客户：统一社会信用代码，组织机构代码 个人客户：居民身份证，军官证，文职干部证，警官证，士兵证，户口簿，临时身份证，其他有效通行旅行证件，护照，学生证，无证件，其他-银行自定义。无法以枚举类型填报的，以“其它-XX”填报，其中“XX”为银行自定义类型。 | H22: C..60 | I22: 删除数据项 | J22: 银行自身实控人，无需每条都报送。
C23: 实控人证件号码 | D23: SKRZJHM | E23: 证件号码 | F23: 002003 | G23: 证件号码。涉及个人身份证件时需按照本规范给定规则进行脱敏处理。 | H23: C..70 | I23: 删除数据项 | J23: 银行自身实控人，无需每条都报送。
A24: GRJCXX | B24: 个人基础信息
C25: 客户英文姓名 | D25: KHYWXM | E25: 客户英文姓名 | F25: 002002 | G25: 英文或拼音。 | H25: C..200 | I25: 删除数据项 | J25: 非监管关注重点
C26: 配偶对应客户号 | D26: PODYKHH | E26: 客户统一编号 | F26: 002001 | G26: 银行自定义的唯一识别客户的标识。供应链融资的填写供应链融资编码。 | H26: C..60 | I26: 删除数据项 | J26: 非监管关注重点
C27: 来源系统 | D27: LYXT | E27: 来源系统 | F27: 002005 | G27: 该客户信息源自的系统名称。 | H27: C..100 | I27: 删除数据项 | J27: 非监管关注重点
C28: 家庭住址 | D28: JTZZ | E28: 地址 | F28: 001007 | G28: 中文描述。个人住址。金融机构以金融机构许可证登记地址为准。集团母公司为境内企业的，按照《企业法人营业执照》中的注册地填报，要写明省（区、市）、地（区、市、州、盟）、县（区、市、旗）。集团母公司为境外企业的，不填报。 | H28: C..400 | I28: 删除数据项 | J28: 非监管关注重点
C29: 家庭电话 | D29: JTDH | E29: 电话 | F29: 001010 | G29: 银行自定义。 | H29: C..30 | I29: 删除数据项 | J29: 统一新增了“联系电话”字段
C30: 移动电话 | D30: YDDH | E30: 电话 | F30: 001010 | G30: 银行自定义。 | H30: C..30 | I30: 删除数据项 | J30: 统一新增了“联系电话”字段
C31: 家庭月收入 | D31: JTYSR | E31: 金额 | F31: 003011 | G31: 与币种相对应金额。 | H31: D20.2 | I31: 删除数据项 | J31: 较多银行未采集
C32: 配偶姓名 | D32: POXM | E32: 姓名 | F32: 001016 | G32: 姓名。 | H32: C..200 | I32: 删除数据项 | J32: 配偶信息可在“个人客户关系表”中查询
C33: 配偶联系电话 | D33: POLXDH | E33: 电话 | F33: 001008 | G33: 手机号码或者区号-固定电话号码。 | H33: C..30 | I33: 删除数据项 | J33: 配偶信息可在“个人客户关系表”中查询
C34: 配偶移动电话 | D34: POYDDH | E34: 电话 | F34: 001008 | G34: 手机号码或者区号-固定电话号码。 | H34: C..30 | I34: 删除数据项 | J34: 配偶信息可在“个人客户关系表”中查询
C35: 配偶证件类别 | D35: POZJLB | E35: 证件类别 | F35: 002002 | G35: 对公客户：统一社会信用代码，没有统一社会信用代码的对公客户填报组织机构代码。 个人客户：居民身份证，军官证，文职干部证，警官证，士兵证，户口簿，临时身份证，其他有效通行旅行证件，护照，学生证，无证件，其他-XX。无法以枚举类型填报的，以“XX”报送，其中“XX”为银行自定义类型。 | H35: C..60 | I35: 删除数据项 | J35: 配偶信息可在“个人客户关系表”中查询
C36: 上黑名单原因 | D36: SHMDYY | E36: 上黑名单原因 | F36: 002010 | G36: 中文字典或中文描述，银行自定义。 | H36: C..400 | I36: 删除数据项 | J36: 非监管关注重点
A37: GRKHGXXX | B37: 个人客户关系信息 | C37: 配偶证件号码 | D37: POZJHM | E37: 证件号码 | F37: 002003 | G37: 证件号码。涉及个人身份证件时需按照本规范给定规则进行脱敏处理。 | H37: C..70
C38: 对应个人客户工作单位名称 | D38: DYGRKHGZDWMC | E38: 名称 | F38: 001001 | G38: 名称应与公章所使用的名称完全一致。银行机构以银保监会金融机构许可证登记名称为准。无独立金融机构许可证的机构，可在本名称中体现出机构特征。 客户名称按照客户的不同类型按如下标准填报。 （1）集团客户，填报银行对该集团授信采用的集团客户名称。视同集团客户填报的供应链融资填报核心企业客户名称。 （2）单一法人客户，经有关部门批准正式使用的全称，与公章所使用的名称完全一致。视同单一法人客户填报的分公司，填报分公司全称，与分公司公章所使用的名称完全一致。 （3）同业客户，经有关部门批准正式使用的客户全称，与客户公章所使用的名称完全一致。 （4）客户是境外法人的，客户名称填报规范的中文翻译；客户是境内涉密法人的，客户名称填报为“*********”。 （5）自然人，与有效证件上的姓名一致。 | H38: C..400 | I38: 删除数据项 | J38: 个人基础信息已有该数据
C39: 对应个人客户工作单位地址 | D39: DYGRKHGZDWDZ | E39: 地址 | F39: 001007 | G39: 中文描述。个人住址。金融机构以金融机构许可证登记地址为准。集团母公司为境内企业的，按照《企业法人营业执照》中的注册地填报，要写明省（区、市）、地（区、市、州、盟）、县（区、市、旗）。集团母公司为境外企业的，不填报。 | H39: C..400 | I39: 删除数据项 | J39: 个人基础信息已有该数据
C40: 对应个人客户工作单位电话 | D40: DYGRKHGZDWDH | E40: 电话 | F40: 001008 | G40: 银行自定义。 | H40: C..30 | I40: 删除数据项 | J40: 个人基础信息已有该数据
A41: GYB | B41: 柜员表
C42: 总行机构代码 | D42: ZXJGDM | E42: 银行机构代码 | F42: 001011 | G42: 人行支付行号 | H42: C..30 | I42: 删除数据项 | J42: 非监管关注重点
C43: 授权范围 | D43: SQFW | E43: 授权范围 | F43: 001026 | G43: 可以授权的业务种类，银行自定义。 | H43: C..30 | I43: 删除数据项 | J43: 该数据项定义不明确，目前大部分银行机构无法填报
C44: 柜员用户级别 | D44: GYYHJB | E44: 柜员用户级别 | F44: 001022 | G44: 银行自定义。 | H44: C..30 | I44: 删除数据项 | J44: 容易与柜员权限级别产生混淆
A45: DGKH | B45: 对公客户
C46: 客户英文名称 | D46: KHYWMC | E46: 客户英文姓名 | F46: 002002 | G46: 英文或拼音。 | H46: C..60 | I46: 删除数据项 | J46: 非监管关注重点
C47: 统一授信标志 | D47: TYSXBZ | E47: 是否标志 | F47: 001002 | G47: 是，否。 | H47: C..4 | I47: 删除数据项 | J47: 通过客户类型可以判断是否为统一授信。
C48: 贷款证号 | D48: DKZH | E48: 贷款卡号 | F48: 002021 | G48: 中国人民银行发放的企业贷款卡号码。 | H48: C..60 | I48: 删除数据项 | J48: 非监管关注重点，只保留统一社会信用代码
C49: 国税证号 | D49: GSZH | E49: 国税证号 | F49: 002022 | G49: 已登记统一社会信用代码的，填18位统一社会信用代码；未登记统一社会信用代码的，按原有方式填写。 | H49: C..60 | I49: 删除数据项 | J49: 非监管关注重点，只保留统一社会信用代码
C50: 地税证号 | D50: DSZH | E50: 地税证号 | F50: 002023 | G50: 已登记统一社会信用代码的，填18位统一社会信用代码；未登记统一社会信用代码的，按原有方式填写。 | H50: C..200 | I50: 删除数据项 | J50: 非监管关注重点，只保留统一社会信用代码
C51: 营业执照号 | D51: YYZZH | E51: 营业执照号 | F51: 002015 | G51: 已登记统一社会信用代码的，填18位统一社会信用代码；未登记统一社会信用代码的，按原有方式填写。 | H51: C..60 | I51: 删除数据项 | J51: 与证件类别重复
C52: 营业执照有效截止日期 | D52: YYZZYXJZRQ | E52: 日期 | F52: 001004 | G52: YYYYMMDD，默认值99991231。 | H52: C8 | I52: 删除数据项 | J52: 与证件类别重复
C53: 母公司客户统一编号 | D53: MGSKHTYBH | E53: 客户统一编号 | F53: 002001 | G53: 银行自定义的唯一识别客户的标识。供应链融资的填写供应链融资编码。 | H53: C..200 | I53: 删除数据项 | J53: 增加了集团客户表，该数据项可以删除
C54: 总资产 | D54: ZZC | E54: 金额 | F54: 003011 | G54: 元。 | H54: D20.2 | I54: 删除数据项 | J54: 增加了对公客户财务信息表，该数据项可以删除
C55: 净资产 | D55: JZC | E55: 金额 | F55: 003011 | G55: 元。 | H55: D20.2 | I55: 删除数据项 | J55: 增加了对公客户财务信息表，该数据项可以删除
C56: 年收入 | D56: NSR | E56: 金额 | F56: 003011 | G56: 元。 | H56: D20.2 | I56: 删除数据项 | J56: 增加了对公客户财务信息表，该数据项可以删除
C57: 币种 | D57: BZ | E57: 币种 | F57: 003016 | G57: 遵循《GB/T 12406-2008 表示货币和资金的代码》的字母代码，如CNY。 | H57: C..2000 | I57: 删除数据项 | J57: 增加了对公客户财务信息表，该数据项可以删除
C58: 传真号码 | D58: CZHM | E58: 传真号码 | F58: 002025 | G58: 区号座机电话。 | H58: I..10 | I58: 删除数据项 | J58: 非监管关注重点
C59: 客户类别 | D59: KHLB | E59: 客户类别 | F59: 002020 | G59: 银监会客户分类标准。对公，对私。 | H59: C..30 | I59: 删除数据项
A60: GLGX | B60: 关联关系
C61: 客户类别 | D61: KHLB | E61: 客户类别 | F61: 002018 | G61: 对公，个人。 | H61: C6 | I61: 删除数据项 | J61: 本表填报对公客户的关联关系，不存在个人。
C62: 录入日期 | D62: LRRQ | E62: 日期 | F62: 001004 | G62: YYYYMMDD，默认值99991231。 | H62: C8 | I62: 删除数据项 | J62: 非监管关注重点
A63: GRHQCKFHZ | B63: 个人活期存款分户账
C64: 交易介质名称 | D64: JYJZMC | E64: 交易介质名称 | F64: 004007 | G64: 卡，折，单，其他。 | H64: C..60 | I64: 删除数据项 | J64: 个人活期存款分户账中增加了外部账号字段
C65: 交易介质号 | D65: JYJZH | E65: 交易介质号 | F65: 004008 | G65: 卡、折、单及其他对应介质号码 | H65: C..4 | I65: 删除数据项 | J65: 个人活期存款分户账中增加了外部账号字段
C66: 统计科目编号 | D66: TJKMBH | E66: 统计科目编号 | F66: 003004 | G66: 参照《中国人民银行关于建立金融基础数据统计制度的通知》（银发[2020]164号）中的统计指标编码填报。如： 单位存款：单位活期存款-12MG4/22MG4；单位定期存款-12MGB/22MGB；单位通知存款-12MGI/22MGI；单位协议存款-12MGR/22MGR；单位协定存款-12MH4/22MH4；单位保证金存款-12MHB/22MHB；单位结构性存款-12MHI/22MHI 个人存款：个人活期存款-12MI2/22MI2；个人定期存款-12MI4/22MI4；个人定活两便存款-12MI6/22MI6；个人通知存款-12MI8/22MI8；个人协议存款是A1411/2411 12MIA/22MIA ；个人协定存款-12MIC/22MIC；个人保证金存款-12MIE/22MIE；个人结构性存款-12MIG/22MIG 普通贷款：单位经营贷款-12M3H/22M3H；单位固定资产贷款-12M3I/22M3I；个人贷款-12M36/22M36；对非居民贷款-12M4E/22M4E ；单位经营贷款-12M5C/22M5C ；单位固定资产贷款-12M5D/22M5D；一般委托贷款-34R03 | H66: C..20 | I66: 删除数据项 | J66: 1、统计科目编号为人行统计报送编号，存在1个编号对应多个科目的情况，2、该编号无法涵盖所有科目。3、该编号不是账务要素，是统计要素
A67: GRHQCKFHZMXJL | B67: 个人活期存款分户账明细记录
A69: GRDQCKFHZ | B69: 个人定期存款分户账
C70: 交易介质名称 | D70: JYJZMC | E70: 交易介质名称 | F70: 004007 | G70: 卡，折，单，其他。 | H70: C..60 | I70: 删除数据项 | J70: 个人定期存款分户账中增加了外部账号字段
C71: 交易介质号 | D71: JYJZH | E71: 交易介质号 | F71: 004008 | G71: 卡、折、单及其他对应介质号码 | H71: C..4 | I71: 删除数据项 | J71: 个人定期存款分户账中增加了外部账号字段
C72: 统计科目编号 | D72: TJKMBH | E72: 统计科目编号 | F72: 003004 | G72: 参照《中国人民银行关于建立金融基础数据统计制度的通知》（银发[2020]164号）中的统计指标编码填报。如： 单位存款：单位活期存款-12MG4/22MG4；单位定期存款-12MGB/22MGB；单位通知存款-12MGI/22MGI；单位协议存款-12MGR/22MGR；单位协定存款-12MH4/22MH4；单位保证金存款-12MHB/22MHB；单位结构性存款-12MHI/22MHI 个人存款：个人活期存款-12MI2/22MI2；个人定期存款-12MI4/22MI4；个人定活两便存款-12MI6/22MI6；个人通知存款-12MI8/22MI8；个人协议存款是A1411/2411 12MIA/22MIA ；个人协定存款-12MIC/22MIC；个人保证金存款-12MIE/22MIE；个人结构性存款-12MIG/22MIG 普通贷款：单位经营贷款-12M3H/22M3H；单位固定资产贷款-12M3I/22M3I；个人贷款-12M36/22M36；对非居民贷款-12M4E/22M4E ；单位经营贷款-12M5C/22M5C ；单位固定资产贷款-12M5D/22M5D；一般委托贷款-34R03 | H72: C..20 | I72: 删除数据项 | J72: 1、统计科目编号为人行统计报送编号，存在1个编号对应多个科目的情况，2、该编号无法涵盖所有科目。3、该编号不是账务要素，是统计要素
A73: GRDQCKFHZMXJL | B73: 个人定期存款分户账明细记录
A75: DGHQCKFHZ | B75: 对公活期存款分户账
C76: 统计科目编号 | D76: TJKMBH | E76: 统计科目编号 | F76: 003004 | G76: 参照《中国人民银行关于建立金融基础数据统计制度的通知》（银发[2020]164号）中的统计指标编码填报。如： 单位存款：单位活期存款-12MG4/22MG4；单位定期存款-12MGB/22MGB；单位通知存款-12MGI/22MGI；单位协议存款-12MGR/22MGR；单位协定存款-12MH4/22MH4；单位保证金存款-12MHB/22MHB；单位结构性存款-12MHI/22MHI 个人存款：个人活期存款-12MI2/22MI2；个人定期存款-12MI4/22MI4；个人定活两便存款-12MI6/22MI6；个人通知存款-12MI8/22MI8；个人协议存款是A1411/2411 12MIA/22MIA ；个人协定存款-12MIC/22MIC；个人保证金存款-12MIE/22MIE；个人结构性存款-12MIG/22MIG 普通贷款：单位经营贷款-12M3H/22M3H；单位固定资产贷款-12M3I/22M3I；个人贷款-12M36/22M36；对非居民贷款-12M4E/22M4E ；单位经营贷款-12M5C/22M5C ；单位固定资产贷款-12M5D/22M5D；一般委托贷款-34R03 | H76: C..20 | I76: 删除数据项 | J76: 1、统计科目编号为人行统计报送编号，存在1个编号对应多个科目的情况，2、该编号无法涵盖所有科目。3、该编号不是账务要素，是统计要素
A77: DGHQCKFHZMXJL | B77: 对公活期存款分户账明细记录
C78: 代办人姓名 | D78: DBRXM | E78: 姓名 | F78: 001019 | G78: 姓名。 | H78: C..60 | I78: 删除数据项 | J78: 对公交易办理一般是单位财务人员，无代办情况
C79: 代办人证件类别 | D79: DBRZJLB | E79: 证件类别 | F79: 002003 | G79: 对公客户：统一社会信用代码，组织机构代码 个人客户：居民身份证，军官证，文职干部证，警官证，士兵证，户口簿，临时身份证，其他有效通行旅行证件，护照，学生证，无证件，其他。 | H79: C..70 | I79: 删除数据项 | J79: 对公交易办理一般是单位财务人员，无代办情况
C80: 代办人证件号码 | D80: DBRZJHM | E80: 证件号码 | F80: 002004 | G80: 证件号码。涉及个人身份证件时需按照本规范给定规则进行脱敏处理。 | H80: C..100 | I80: 删除数据项 | J80: 对公交易办理一般是单位财务人员，无代办情况
A81: DGDQCKFHZ | B81: 对公定期存款分户账
C82: 统计科目编号 | D82: TJKMBH | E82: 统计科目编号 | F82: 003004 | G82: 参照《中国人民银行关于建立金融基础数据统计制度的通知》（银发[2020]164号）中的统计指标编码填报。如： 单位存款：单位活期存款-12MG4/22MG4；单位定期存款-12MGB/22MGB；单位通知存款-12MGI/22MGI；单位协议存款-12MGR/22MGR；单位协定存款-12MH4/22MH4；单位保证金存款-12MHB/22MHB；单位结构性存款-12MHI/22MHI 个人存款：个人活期存款-12MI2/22MI2；个人定期存款-12MI4/22MI4；个人定活两便存款-12MI6/22MI6；个人通知存款-12MI8/22MI8；个人协议存款是A1411/2411 12MIA/22MIA ；个人协定存款-12MIC/22MIC；个人保证金存款-12MIE/22MIE；个人结构性存款-12MIG/22MIG 普通贷款：单位经营贷款-12M3H/22M3H；单位固定资产贷款-12M3I/22M3I；个人贷款-12M36/22M36；对非居民贷款-12M4E/22M4E ；单位经营贷款-12M5C/22M5C ；单位固定资产贷款-12M5D/22M5D；一般委托贷款-34R03 | H82: C..20 | I82: 删除数据项 | J82: 1、统计科目编号为人行统计报送编号，存在1个编号对应多个科目的情况，2、该编号无法涵盖所有科目。3、该编号不是账务要素，是统计要素
A83: DGDQCKFHZMXJL | B83: 对公定期存款分户账明细记录
C84: 代办人姓名 | D84: DBRXM | E84: 姓名 | F84: 001019 | G84: 姓名。 | H84: C..60 | I84: 删除数据项 | J84: 对公交易办理一般是单位财务人员，无代办情况
C85: 代办人证件类别 | D85: DBRZJLB | E85: 证件类别 | F85: 002003 | G85: 对公客户：统一社会信用代码，组织机构代码 个人客户：居民身份证，军官证，文职干部证，警官证，士兵证，户口簿，临时身份证，其他有效通行旅行证件，护照，学生证，无证件，其他。 | H85: C..70 | I85: 删除数据项 | J85: 对公交易办理一般是单位财务人员，无代办情况
C86: 代办人证件号码 | D86: DBRZJHM | E86: 证件号码 | F86: 002004 | G86: 证件号码。涉及个人身份证件时需按照本规范给定规则进行脱敏处理。 | H86: C..100 | I86: 删除数据项 | J86: 对公交易办理一般是单位财务人员，无代办情况
A87: NBFHZ | B87: 内部分户账
C88: 统计科目编号 | D88: TJKMBH | E88: 统计科目编号 | F88: 003004 | G88: 参照《中国人民银行关于建立金融基础数据统计制度的通知》（银发[2020]164号）中的统计指标编码填报。如： 单位存款：单位活期存款-12MG4/22MG4；单位定期存款-12MGB/22MGB；单位通知存款-12MGI/22MGI；单位协议存款-12MGR/22MGR；单位协定存款-12MH4/22MH4；单位保证金存款-12MHB/22MHB；单位结构性存款-12MHI/22MHI 个人存款：个人活期存款-12MI2/22MI2；个人定期存款-12MI4/22MI4；个人定活两便存款-12MI6/22MI6；个人通知存款-12MI8/22MI8；个人协议存款是A1411/2411 12MIA/22MIA ；个人协定存款-12MIC/22MIC；个人保证金存款-12MIE/22MIE；个人结构性存款-12MIG/22MIG 普通贷款：单位经营贷款-12M3H/22M3H；单位固定资产贷款-12M3I/22M3I；个人贷款-12M36/22M36；对非居民贷款-12M4E/22M4E ；单位经营贷款-12M5C/22M5C ；单位固定资产贷款-12M5D/22M5D；一般委托贷款-34R03 | H88: C..20 | I88: 删除数据项 | J88: 1、统计科目编号为人行统计报送编号，存在1个编号对应多个科目的情况，2、该编号无法涵盖所有科目。3、该编号不是账务要素，是统计要素
C89: 内部分户账账户类型 | D89: NBFHZZHLX | E89: 内部分户账账户类型 | F89: 003027 | G89: 中文描述，银行自定义。 | H89: C..60 | I89: 删除数据项 | J89: 枚举值不明确，机构难以填报。
A90: NBFHZMXJL | B90: 内部分户账明细记录
A92: GRXDFHZ | B92: 个人信贷分户账
C93: 统计科目编号 | D93: TJKMBH | E93: 统计科目编号 | F93: 003004 | G93: 参照《中国人民银行关于建立金融基础数据统计制度的通知》（银发[2020]164号）中的统计指标编码填报。如： 单位存款：单位活期存款-12MG4/22MG4；单位定期存款-12MGB/22MGB；单位通知存款-12MGI/22MGI；单位协议存款-12MGR/22MGR；单位协定存款-12MH4/22MH4；单位保证金存款-12MHB/22MHB；单位结构性存款-12MHI/22MHI 个人存款：个人活期存款-12MI2/22MI2；个人定期存款-12MI4/22MI4；个人定活两便存款-12MI6/22MI6；个人通知存款-12MI8/22MI8；个人协议存款是A1411/2411 12MIA/22MIA ；个人协定存款-12MIC/22MIC；个人保证金存款-12MIE/22MIE；个人结构性存款-12MIG/22MIG 普通贷款：单位经营贷款-12M3H/22M3H；单位固定资产贷款-12M3I/22M3I；个人贷款-12M36/22M36；对非居民贷款-12M4E/22M4E ；单位经营贷款-12M5C/22M5C ；单位固定资产贷款-12M5D/22M5D；一般委托贷款-34R03 | H93: C..20 | I93: 删除数据项 | J93: 信贷业务借据中已经对业务种类进行细分，且人行统计指标编码均为代码，不利于检查人员理解，建议删除
C94: 会计核算方式 | D94: KJHSFS | E94: 会计核算方式 | F94: 003041 | G94: 表内,表外,表内及表外 | H94: 0 | I94: 删除数据项 | J94: 表内或表外通过信贷业务种类进行划分
C95: 逾期利率 | D95: DKLL | E95: 利率 | F95: 003028 | G95: 百分比为单位，即1/100，一般为年利。 | H95: C..60 | I95: 删除数据项 | J95: 非监管关注重点
C96: 正常本金 | D96: ZCBJ | E96: 余额 | F96: 003012 | G96: 元。 | H96: D20.2 | I96: 删除数据项 | J96: 新增贷款余额数据项
C97: 逾期本金 | D97: YQBJ | E97: 余额 | F97: 003012 | G97: 元。 | H97: D20.2 | I97: 删除数据项 | J97: 新增贷款余额数据项
C98: 应收利息 | D98: YSLX | E98: 余额 | F98: 003012 | G98: 元。 | H98: D20.2 | I98: 删除数据项 | J98: 该数据项改为表内欠息月，在个人信贷业务借据中可查询
C99: 表外欠息余额 | D99: BWQXYE | E99: 余额 | F99: 003012 | G99: 元。 | H99: D20.2 | I99: 删除数据项 | J99: 该数据项在个人信贷业务借据中可查询
C100: 贷款期限 | D100: DKQX | E100: 贷款期限 | F100: 005038 | G100: 实际到期日减去起始日，按天表示。 | H100: I..4 | I100: 删除数据项 | J100: 实际到期日期减发放日期即可得出贷款期限，不必单列数据项
C101: 起息日期 | D101: QXRQ | E101: 日期 | F101: 001005 | G101: YYYYMMDD，默认值99991231。 | H101: C6 | I101: 删除数据项 | J101: 数据项“发放日期”即为起息日期
C102: 逾期日期 | D102: YQRQ | E102: 日期 | F102: 001005 | G102: YYYYMMDD，默认值99991231。 | H102: C6 | I102: 删除数据项 | J102: 该数据项在个人信贷业务借据中可查询
C103: 还款账号 | D103: HKZH | E103: 账号 | F103: 003001 | G103: 系统内最细一级的账号，无唯一性约束，不需要和序号、子序号等做拼接。 | H103: C..60 | I103: 删除数据项 | J103: 该数据项在个人信贷业务借据中可查询
C104: 贷款入账账号 | D104: DKRZZH | E104: 账号 | F104: 003001 | G104: 系统内最细一级的账号，无唯一性约束，不需要和序号、子序号等做拼接。 | H104: C..60 | I104: 删除数据项 | J104: 该数据项在个人信贷业务借据中可查询
C105: 信贷员姓名 | D105: XDYXM | E105: 姓名 | F105: 001019 | G105: 姓名。 | H105: C..60 | I105: 删除数据项 | J105: 该数据项在个人信贷业务借据中可查询
...
